{"version":2,"kind":"Notebook","sha256":"b7acf3f578af94be547842b01251674d90c3d48886ef99047bffa7e91dc81da2","slug":"index","location":"/week01/L01.01_welcome.ipynb","dependencies":[],"frontmatter":{"title":"Welcome","content_includes_title":false,"kernelspec":{"name":"julia-1.10","display_name":"Julia 1.10.4","language":"julia"},"authors":[{"nameParsed":{"literal":"Spencer Lyon","given":"Spencer","family":"Lyon"},"name":"Spencer Lyon","orcid":"0009-0001-6461-885X","email":"spencer.lyon@ucf.edu","affiliations":["University of Central Florida","Valorum Data"],"id":"contributors-myst-generated-uid-0","corresponding":true}],"affiliations":[{"id":"University of Central Florida","name":"University of Central Florida"},{"id":"Valorum Data","name":"Valorum Data"}],"exports":[{"format":"ipynb","filename":"L01.01_welcome.ipynb","url":"/build/L01.01_welcome-8940926708ce80c7e8e6456975cf4c5c.ipynb"}]},"widgets":{},"mdast":{"type":"root","children":[{"type":"block","kind":"notebook-content","data":{"slideshow":{"slide_type":"slide"},"tags":[]},"children":[{"type":"blockquote","position":{"start":{"line":3,"column":1},"end":{"line":5,"column":1}},"children":[{"type":"paragraph","position":{"start":{"line":3,"column":1},"end":{"line":3,"column":1}},"children":[{"type":"text","value":"Computational Analysis of Social Complexity","position":{"start":{"line":3,"column":1},"end":{"line":3,"column":1}},"key":"Ao4AI7x26a"}],"key":"k0aX88N641"},{"type":"paragraph","position":{"start":{"line":5,"column":1},"end":{"line":5,"column":1}},"children":[{"type":"text","value":"Fall 2025, Spencer Lyon","position":{"start":{"line":5,"column":1},"end":{"line":5,"column":1}},"key":"cxYmOlhEvn"}],"key":"fSx3E9utOF"}],"key":"NJ8JHBmN87"},{"type":"paragraph","position":{"start":{"line":7,"column":1},"end":{"line":7,"column":1}},"children":[{"type":"text","value":"Welcome to week 1!","position":{"start":{"line":7,"column":1},"end":{"line":7,"column":1}},"key":"Gq5udUjJ3I"}],"key":"kbfS20tH0F"},{"type":"paragraph","position":{"start":{"line":9,"column":1},"end":{"line":9,"column":1}},"children":[{"type":"text","value":"This week we will get to know eachother and get on the same page with respect to what this class is all about.","position":{"start":{"line":9,"column":1},"end":{"line":9,"column":1}},"key":"pnxDCNnzSK"}],"key":"DMf0Hbh1Yi"},{"type":"paragraph","position":{"start":{"line":11,"column":1},"end":{"line":11,"column":1}},"children":[{"type":"text","value":"We will also dive right in to the computational infrastructure we will need by installing the Julia programming langauge and learning a bit about how to use it.","position":{"start":{"line":11,"column":1},"end":{"line":11,"column":1}},"key":"If8KOLXCac"}],"key":"fzv8Up0MlO"},{"type":"paragraph","position":{"start":{"line":13,"column":1},"end":{"line":13,"column":1}},"children":[{"type":"text","value":"Each week lecture notes will be distributed as a collection of Jupyter notebooks. The notebooks will follow a strict naming convention, where each notebook has a name such as ","position":{"start":{"line":13,"column":1},"end":{"line":13,"column":1}},"key":"UI35ybmSU1"},{"type":"inlineCode","value":"L@@.##_XXX.ipynb","position":{"start":{"line":13,"column":1},"end":{"line":13,"column":1}},"key":"yPtNGVCsUj"},{"type":"text","value":" where ","position":{"start":{"line":13,"column":1},"end":{"line":13,"column":1}},"key":"pfHltryxwc"},{"type":"inlineCode","value":"@@","position":{"start":{"line":13,"column":1},"end":{"line":13,"column":1}},"key":"i7a5X6FQ8a"},{"type":"text","value":" is a two digit lecture number and ","position":{"start":{"line":13,"column":1},"end":{"line":13,"column":1}},"key":"INlYaVbVtq"},{"type":"inlineCode","value":"##","position":{"start":{"line":13,"column":1},"end":{"line":13,"column":1}},"key":"YK9Ptfjgd0"},{"type":"text","value":" is a two digit file number and ","position":{"start":{"line":13,"column":1},"end":{"line":13,"column":1}},"key":"MLkGP8eLin"},{"type":"inlineCode","value":"XXX","position":{"start":{"line":13,"column":1},"end":{"line":13,"column":1}},"key":"XPl9usSmPP"},{"type":"text","value":" is one or more words describing the content of the notebook. We will work through the notebooks in the order indicated by the ","position":{"start":{"line":13,"column":1},"end":{"line":13,"column":1}},"key":"uejMeuQCJS"},{"type":"inlineCode","value":"##","position":{"start":{"line":13,"column":1},"end":{"line":13,"column":1}},"key":"kou26fwcvY"},{"type":"text","value":". The ","position":{"start":{"line":13,"column":1},"end":{"line":13,"column":1}},"key":"B8Bqw4V5fs"},{"type":"inlineCode","value":"XXX","position":{"start":{"line":13,"column":1},"end":{"line":13,"column":1}},"key":"tWSDfsB0TK"},{"type":"text","value":" are to provide easier access when reviewing notes after class.","position":{"start":{"line":13,"column":1},"end":{"line":13,"column":1}},"key":"S1hwTC9XmT"}],"key":"RjRbIwYl3q"}],"visibility":"show","key":"a0RdseBUjx"},{"type":"block","kind":"notebook-content","data":{"slideshow":{"slide_type":"slide"},"tags":[]},"children":[{"type":"heading","depth":2,"position":{"start":{"line":1,"column":1},"end":{"line":1,"column":1}},"children":[{"type":"text","value":"About Me","position":{"start":{"line":1,"column":1},"end":{"line":1,"column":1}},"key":"CWyeQhF2Od"}],"identifier":"about-me","label":"About Me","html_id":"about-me","implicit":true,"key":"buOmzX7Miu"},{"type":"list","ordered":false,"spread":false,"position":{"start":{"line":3,"column":1},"end":{"line":9,"column":1}},"children":[{"type":"listItem","spread":true,"position":{"start":{"line":3,"column":1},"end":{"line":3,"column":1}},"children":[{"type":"text","value":"Spencer Lyon (","position":{"start":{"line":3,"column":1},"end":{"line":3,"column":1}},"key":"tJVT1GNuW3"},{"type":"link","url":"mailto:spencer.lyon@ucf.edu","position":{"start":{"line":3,"column":1},"end":{"line":3,"column":1}},"children":[{"type":"text","value":"spencer​.lyon@ucf​.edu","position":{"start":{"line":3,"column":1},"end":{"line":3,"column":1}},"key":"WDRNJ6lD4x"}],"urlSource":"mailto:spencer.lyon@ucf.edu","key":"jXHWNXemVx"},{"type":"text","value":")","position":{"start":{"line":3,"column":1},"end":{"line":3,"column":1}},"key":"eQUTSXfrCl"}],"key":"siB2tWnIDt"},{"type":"listItem","spread":true,"position":{"start":{"line":4,"column":1},"end":{"line":4,"column":1}},"children":[{"type":"text","value":"Economics PhD from NYU (2018)","position":{"start":{"line":4,"column":1},"end":{"line":4,"column":1}},"key":"G69rkCdUW1"}],"key":"bydC4L4WsY"},{"type":"listItem","spread":true,"position":{"start":{"line":5,"column":1},"end":{"line":6,"column":1}},"children":[{"type":"text","value":"Love to teach: mostly economics, data science, AI/ML – all have\nprogramming/computational element","position":{"start":{"line":5,"column":1},"end":{"line":5,"column":1}},"key":"mFr69gmxtU"}],"key":"PUTySPLXPl"},{"type":"listItem","spread":true,"position":{"start":{"line":7,"column":1},"end":{"line":7,"column":1}},"children":[{"type":"text","value":"Moved to Orlando in July 2018 with wife and 5 (yes!) kids","position":{"start":{"line":7,"column":1},"end":{"line":7,"column":1}},"key":"QlVNv03h0C"}],"key":"eybeADvthk"},{"type":"listItem","spread":true,"position":{"start":{"line":8,"column":1},"end":{"line":8,"column":1}},"children":[{"type":"text","value":"Run consulting (training/projects) business:   Valorum Data","position":{"start":{"line":8,"column":1},"end":{"line":8,"column":1}},"key":"rkMlWfVqtI"}],"key":"rGLRnYdLEp"},{"type":"listItem","spread":true,"position":{"start":{"line":9,"column":1},"end":{"line":9,"column":1}},"children":[{"type":"text","value":"Working on a couple startups","position":{"start":{"line":9,"column":1},"end":{"line":9,"column":1}},"key":"S0TuspCeUB"}],"key":"myGBFksJhG"}],"key":"yQ3kdTj69a"}],"visibility":"show","key":"TtcEqEz2a4"},{"type":"block","kind":"notebook-content","data":{"slideshow":{"slide_type":"subslide"},"tags":[]},"children":[{"type":"heading","depth":2,"position":{"start":{"line":1,"column":1},"end":{"line":1,"column":1}},"children":[{"type":"text","value":"About you","position":{"start":{"line":1,"column":1},"end":{"line":1,"column":1}},"key":"ibtKk485Cf"}],"identifier":"about-you","label":"About you","html_id":"about-you","implicit":true,"key":"VttzIWCLvY"},{"type":"list","ordered":false,"spread":false,"position":{"start":{"line":3,"column":1},"end":{"line":6,"column":1}},"children":[{"type":"listItem","spread":true,"position":{"start":{"line":3,"column":1},"end":{"line":3,"column":1}},"children":[{"type":"text","value":"Background?","position":{"start":{"line":3,"column":1},"end":{"line":3,"column":1}},"key":"vRxIwxU9Pe"}],"key":"kjaCpp2Dg3"},{"type":"listItem","spread":true,"position":{"start":{"line":4,"column":1},"end":{"line":4,"column":1}},"children":[{"type":"text","value":"Progress in program?","position":{"start":{"line":4,"column":1},"end":{"line":4,"column":1}},"key":"QC1pVQt2rE"}],"key":"h4wyivqmtA"},{"type":"listItem","spread":true,"position":{"start":{"line":5,"column":1},"end":{"line":5,"column":1}},"children":[{"type":"text","value":"Areas of interest? (meaningful answers here! they matter…)","position":{"start":{"line":5,"column":1},"end":{"line":5,"column":1}},"key":"a32FnVcBPg"}],"key":"ugQWlkmYcx"},{"type":"listItem","spread":true,"position":{"start":{"line":6,"column":1},"end":{"line":6,"column":1}},"children":[{"type":"text","value":"Rumors about the course?","position":{"start":{"line":6,"column":1},"end":{"line":6,"column":1}},"key":"yFTCy1Dt70"}],"key":"dYuYaNPbM1"}],"key":"xMoJpdPCS6"}],"visibility":"show","key":"x4JmoEGWmR"},{"type":"block","kind":"notebook-content","data":{"slideshow":{"slide_type":"subslide"},"tags":[]},"children":[{"type":"heading","depth":2,"position":{"start":{"line":1,"column":1},"end":{"line":1,"column":1}},"children":[{"type":"text","value":"About the course","position":{"start":{"line":1,"column":1},"end":{"line":1,"column":1}},"key":"OXDpOSwNEg"}],"identifier":"about-the-course","label":"About the course","html_id":"about-the-course","implicit":true,"key":"ag1SWVxNul"},{"type":"list","ordered":false,"spread":false,"position":{"start":{"line":3,"column":1},"end":{"line":7,"column":1}},"children":[{"type":"listItem","spread":true,"position":{"start":{"line":3,"column":1},"end":{"line":3,"column":1}},"children":[{"type":"text","value":"Interdisciplinary by nature","position":{"start":{"line":3,"column":1},"end":{"line":3,"column":1}},"key":"kB59aPoRe5"}],"key":"uIEWF33sxG"},{"type":"listItem","spread":true,"position":{"start":{"line":4,"column":1},"end":{"line":7,"column":1}},"children":[{"type":"text","value":"“Living course”: only been taught a handful of times, content is flexible","position":{"start":{"line":4,"column":1},"end":{"line":4,"column":1}},"key":"qX7ceY8TLY"},{"type":"list","ordered":false,"spread":false,"position":{"start":{"line":5,"column":1},"end":{"line":7,"column":1}},"children":[{"type":"listItem","spread":true,"position":{"start":{"line":5,"column":1},"end":{"line":5,"column":1}},"children":[{"type":"text","value":"More ideas/topics than time!","position":{"start":{"line":5,"column":1},"end":{"line":5,"column":1}},"key":"ZKlOS47HWj"}],"key":"mI6dJOc97n"},{"type":"listItem","spread":true,"position":{"start":{"line":6,"column":1},"end":{"line":6,"column":1}},"children":[{"type":"text","value":"Has been altered fairly significantly over the past few years (but the heart/soul of the course remains the same)","position":{"start":{"line":6,"column":1},"end":{"line":6,"column":1}},"key":"RnznDb0Y2V"}],"key":"XpNSY7ITsC"},{"type":"listItem","spread":true,"position":{"start":{"line":7,"column":1},"end":{"line":7,"column":1}},"children":[{"type":"text","value":"No required topics or standard textbook, so we get to pick!","position":{"start":{"line":7,"column":1},"end":{"line":7,"column":1}},"key":"R0tsuHmzkc"}],"key":"nAYhb6Gpwz"}],"key":"uElo7geRn8"}],"key":"qXzkQSftTq"}],"key":"frRWiBwtuF"}],"visibility":"show","key":"bS0Hj4XDpj"},{"type":"block","kind":"notebook-content","data":{"slideshow":{"slide_type":"subslide"},"tags":[]},"children":[{"type":"list","ordered":false,"spread":false,"position":{"start":{"line":1,"column":1},"end":{"line":7,"column":1}},"children":[{"type":"listItem","spread":true,"position":{"start":{"line":1,"column":1},"end":{"line":7,"column":1}},"children":[{"type":"text","value":"Theoretical concepts","position":{"start":{"line":1,"column":1},"end":{"line":1,"column":1}},"key":"TmtAUWSG9L"},{"type":"list","ordered":false,"spread":false,"position":{"start":{"line":2,"column":1},"end":{"line":7,"column":1}},"children":[{"type":"listItem","spread":true,"position":{"start":{"line":2,"column":1},"end":{"line":2,"column":1}},"children":[{"type":"text","value":"Graphs: less detail than network science course, but more algorithms","position":{"start":{"line":2,"column":1},"end":{"line":2,"column":1}},"key":"qKQzVJNaPX"}],"key":"Byb4CYPshU"},{"type":"listItem","spread":true,"position":{"start":{"line":3,"column":1},"end":{"line":3,"column":1}},"children":[{"type":"text","value":"Game Theory: strategic interaction/competition","position":{"start":{"line":3,"column":1},"end":{"line":3,"column":1}},"key":"bqBB6i67IV"}],"key":"uYsUZmzurN"},{"type":"listItem","spread":true,"position":{"start":{"line":4,"column":1},"end":{"line":4,"column":1}},"children":[{"type":"text","value":"Agent Based Models: simulation of rule based systems","position":{"start":{"line":4,"column":1},"end":{"line":4,"column":1}},"key":"jxVYc3yPu0"}],"key":"b9fc41tUbd"},{"type":"listItem","spread":true,"position":{"start":{"line":5,"column":1},"end":{"line":5,"column":1}},"children":[{"type":"text","value":"Auction theory: Game theory at scale in bidding markets","position":{"start":{"line":5,"column":1},"end":{"line":5,"column":1}},"key":"Xf923MXQT6"}],"key":"wZ3UKwPhIe"},{"type":"listItem","spread":true,"position":{"start":{"line":6,"column":1},"end":{"line":6,"column":1}},"children":[{"type":"text","value":"Blockchain: cryptographically secure, public, distributed ledger","position":{"start":{"line":6,"column":1},"end":{"line":6,"column":1}},"key":"SkQFGmFX3K"}],"key":"wtebP8vY2t"},{"type":"listItem","spread":true,"position":{"start":{"line":7,"column":1},"end":{"line":7,"column":1}},"children":[{"type":"text","value":"Social, information, financial networks","position":{"start":{"line":7,"column":1},"end":{"line":7,"column":1}},"key":"Al0oQX12tI"}],"key":"HVrpk9sWdn"}],"key":"TGJnIO2YHo"}],"key":"Tx7RTvYbKt"}],"key":"J774QzFb1h"}],"visibility":"show","key":"gPdTovfOB5"},{"type":"block","kind":"notebook-content","data":{"slideshow":{"slide_type":"subslide"},"tags":[]},"children":[{"type":"list","ordered":false,"spread":false,"position":{"start":{"line":1,"column":1},"end":{"line":5,"column":1}},"children":[{"type":"listItem","spread":true,"position":{"start":{"line":1,"column":1},"end":{"line":5,"column":1}},"children":[{"type":"text","value":"Applications","position":{"start":{"line":1,"column":1},"end":{"line":1,"column":1}},"key":"Ag0G9l3FoG"},{"type":"list","ordered":false,"spread":false,"position":{"start":{"line":2,"column":1},"end":{"line":5,"column":1}},"children":[{"type":"listItem","spread":true,"position":{"start":{"line":2,"column":1},"end":{"line":2,"column":1}},"children":[{"type":"text","value":"Twitter","position":{"start":{"line":2,"column":1},"end":{"line":2,"column":1}},"key":"VKXfwPLqZ5"}],"key":"ppaHbJhtbH"},{"type":"listItem","spread":true,"position":{"start":{"line":3,"column":1},"end":{"line":4,"column":1}},"children":[{"type":"text","value":"Economic markets and trade\nnetwork","position":{"start":{"line":3,"column":1},"end":{"line":3,"column":1}},"key":"tZQFB0Vkj6"}],"key":"Vd3XQSVD24"},{"type":"listItem","spread":true,"position":{"start":{"line":5,"column":1},"end":{"line":5,"column":1}},"children":[{"type":"text","value":"More...","position":{"start":{"line":5,"column":1},"end":{"line":5,"column":1}},"key":"jyBql7rvnv"}],"key":"F49ILruSMM"}],"key":"gUQELgHC5u"}],"key":"ruAg1fIS7j"}],"key":"i3QommZ7Bp"}],"visibility":"show","key":"RvjwXWE3k4"},{"type":"block","kind":"notebook-content","data":{"slideshow":{"slide_type":"subslide"},"tags":[]},"children":[{"type":"heading","depth":2,"position":{"start":{"line":1,"column":1},"end":{"line":1,"column":1}},"children":[{"type":"text","value":"Expectations","position":{"start":{"line":1,"column":1},"end":{"line":1,"column":1}},"key":"wciSgQZowx"}],"identifier":"expectations","label":"Expectations","html_id":"expectations","implicit":true,"key":"ZDOhKV6dd2"},{"type":"list","ordered":false,"spread":false,"position":{"start":{"line":3,"column":1},"end":{"line":22,"column":1}},"children":[{"type":"listItem","spread":true,"position":{"start":{"line":3,"column":1},"end":{"line":5,"column":1}},"children":[{"type":"text","value":"Take the time in the first 2 weeks to learn Julia","position":{"start":{"line":3,"column":1},"end":{"line":3,"column":1}},"key":"VHmrBTgatI"},{"type":"list","ordered":false,"spread":false,"position":{"start":{"line":4,"column":1},"end":{"line":5,"column":1}},"children":[{"type":"listItem","spread":true,"position":{"start":{"line":4,"column":1},"end":{"line":4,"column":1}},"children":[{"type":"text","value":"You’ll be glad you did","position":{"start":{"line":4,"column":1},"end":{"line":4,"column":1}},"key":"pJ6Rroyy3z"}],"key":"uWzBzEzRD8"},{"type":"listItem","spread":true,"position":{"start":{"line":5,"column":1},"end":{"line":5,"column":1}},"children":[{"type":"text","value":"Content moves quick and you don’t want syntax/programming to distract you or hold you back","position":{"start":{"line":5,"column":1},"end":{"line":5,"column":1}},"key":"Qre0yWF3TN"}],"key":"LncqJBJZME"}],"key":"g8aqg9I5as"}],"key":"vJs3gpO4RJ"},{"type":"listItem","spread":true,"position":{"start":{"line":6,"column":1},"end":{"line":6,"column":1}},"children":[{"type":"text","value":"Study reading assignments ","position":{"start":{"line":6,"column":1},"end":{"line":6,"column":1}},"key":"hg4YlxAhzy"},{"type":"strong","position":{"start":{"line":6,"column":1},"end":{"line":6,"column":1}},"children":[{"type":"text","value":"before class","position":{"start":{"line":6,"column":1},"end":{"line":6,"column":1}},"key":"HLjBzdXTDr"}],"key":"yAzWQ7K2AK"}],"key":"FScQyybsAM"},{"type":"listItem","spread":true,"position":{"start":{"line":7,"column":1},"end":{"line":7,"column":1}},"children":[{"type":"text","value":"Complete assignments on time -- no exceptions","position":{"start":{"line":7,"column":1},"end":{"line":7,"column":1}},"key":"P7f3VukCux"}],"key":"fFuax0vhWv"},{"type":"listItem","spread":true,"position":{"start":{"line":8,"column":1},"end":{"line":8,"column":1}},"children":[{"type":"text","value":"Participate in in-class ","position":{"start":{"line":8,"column":1},"end":{"line":8,"column":1}},"key":"M0I6X1EsrL"},{"type":"emphasis","position":{"start":{"line":8,"column":1},"end":{"line":8,"column":1}},"children":[{"type":"text","value":"discussions","position":{"start":{"line":8,"column":1},"end":{"line":8,"column":1}},"key":"LLgRPjpCI2"}],"key":"kBqjMXotJy"}],"key":"lPaYr1EzTG"},{"type":"listItem","spread":true,"position":{"start":{"line":9,"column":1},"end":{"line":9,"column":1}},"children":[{"type":"text","value":"Spend ~3-6 hours outside of class per week","position":{"start":{"line":9,"column":1},"end":{"line":9,"column":1}},"key":"g05PMPsy5Y"}],"key":"t5WjqDSQ6T"},{"type":"listItem","spread":true,"position":{"start":{"line":10,"column":1},"end":{"line":14,"column":1}},"children":[{"type":"text","value":"Communication","position":{"start":{"line":10,"column":1},"end":{"line":10,"column":1}},"key":"q1rp9mz4D7"},{"type":"list","ordered":false,"spread":false,"position":{"start":{"line":11,"column":1},"end":{"line":14,"column":1}},"children":[{"type":"listItem","spread":true,"position":{"start":{"line":11,"column":1},"end":{"line":11,"column":1}},"children":[{"type":"text","value":"Post ","position":{"start":{"line":11,"column":1},"end":{"line":11,"column":1}},"key":"SlLUYD9vpj"},{"type":"strong","position":{"start":{"line":11,"column":1},"end":{"line":11,"column":1}},"children":[{"type":"text","value":"all","position":{"start":{"line":11,"column":1},"end":{"line":11,"column":1}},"key":"NX3zcYEjeB"}],"key":"eesbRbStCq"},{"type":"text","value":" content related questions to class discussion forum","position":{"start":{"line":11,"column":1},"end":{"line":11,"column":1}},"key":"bsMxN0UlEw"}],"key":"UNHhRAn9r7"},{"type":"listItem","spread":true,"position":{"start":{"line":12,"column":1},"end":{"line":12,"column":1}},"children":[{"type":"text","value":"Respond to peers’ questions and engage in discussions","position":{"start":{"line":12,"column":1},"end":{"line":12,"column":1}},"key":"GpylLHrJ64"}],"key":"lT99GGyU9E"},{"type":"listItem","spread":true,"position":{"start":{"line":13,"column":1},"end":{"line":13,"column":1}},"children":[{"type":"text","value":"Personal questions should go directly to me via email","position":{"start":{"line":13,"column":1},"end":{"line":13,"column":1}},"key":"sasqBVtmuG"}],"key":"s62bCHlTis"},{"type":"listItem","spread":true,"position":{"start":{"line":14,"column":1},"end":{"line":14,"column":1}},"children":[{"type":"text","value":"I do not use email on Sunday. Other days I will respond within 48 hours.","position":{"start":{"line":14,"column":1},"end":{"line":14,"column":1}},"key":"PX1GS7eH8Q"}],"key":"e3ob0atB7T"}],"key":"bcWVtwE5ql"}],"key":"hsoMOmeeTP"},{"type":"listItem","spread":true,"position":{"start":{"line":15,"column":1},"end":{"line":22,"column":1}},"children":[{"type":"text","value":"Deliverables","position":{"start":{"line":15,"column":1},"end":{"line":15,"column":1}},"key":"Y1uCMm3hiC"},{"type":"list","ordered":false,"spread":false,"position":{"start":{"line":16,"column":1},"end":{"line":22,"column":1}},"children":[{"type":"listItem","spread":true,"position":{"start":{"line":16,"column":1},"end":{"line":16,"column":1}},"children":[{"type":"text","value":"Homework (~8 – 30%)","position":{"start":{"line":16,"column":1},"end":{"line":16,"column":1}},"key":"tONbPhaaq5"}],"key":"X2XNQ9Tay4"},{"type":"listItem","spread":true,"position":{"start":{"line":17,"column":1},"end":{"line":17,"column":1}},"children":[{"type":"text","value":"Exam (2 – 30%)","position":{"start":{"line":17,"column":1},"end":{"line":17,"column":1}},"key":"DcZUzIF3vh"}],"key":"s6UneLfhds"},{"type":"listItem","spread":true,"position":{"start":{"line":18,"column":1},"end":{"line":18,"column":1}},"children":[{"type":"text","value":"Projects (2 – 30%)","position":{"start":{"line":18,"column":1},"end":{"line":18,"column":1}},"key":"cgATrh3KKI"}],"key":"gq7SvkizW8"},{"type":"listItem","spread":true,"position":{"start":{"line":19,"column":1},"end":{"line":22,"column":1}},"children":[{"type":"text","value":"Citizenship (throughout - 10%)","position":{"start":{"line":19,"column":1},"end":{"line":19,"column":1}},"key":"EcB5Efxj7d"},{"type":"list","ordered":false,"spread":false,"position":{"start":{"line":20,"column":1},"end":{"line":22,"column":1}},"children":[{"type":"listItem","spread":true,"position":{"start":{"line":20,"column":1},"end":{"line":20,"column":1}},"children":[{"type":"text","value":"First best: attend class in person, actively participate","position":{"start":{"line":20,"column":1},"end":{"line":20,"column":1}},"key":"opziEP2H5Q"}],"key":"aIyEelVfha"},{"type":"listItem","spread":true,"position":{"start":{"line":21,"column":1},"end":{"line":21,"column":1}},"children":[{"type":"text","value":"Acceptable: attend virtually, but keep video on and be ready to speak up when called on","position":{"start":{"line":21,"column":1},"end":{"line":21,"column":1}},"key":"AzHeRnWq5p"}],"key":"wrpFpKR3pv"},{"type":"listItem","spread":true,"position":{"start":{"line":22,"column":1},"end":{"line":22,"column":1}},"children":[{"type":"text","value":"Unacceptable: attend virtually, but keep video off and/or don’t participate in discussions","position":{"start":{"line":22,"column":1},"end":{"line":22,"column":1}},"key":"KnaulNQiJy"}],"key":"c4C3Co2ENJ"}],"key":"KdoCRgjdSC"}],"key":"B8EaONl8lt"}],"key":"VX13QZbzxk"}],"key":"TOBcMDdDFi"}],"key":"zzrtTeupUb"}],"visibility":"show","key":"vcZtGdY9z8"},{"type":"block","kind":"notebook-content","data":{"slideshow":{"slide_type":"slide"},"tags":[]},"children":[{"type":"heading","depth":2,"position":{"start":{"line":1,"column":1},"end":{"line":1,"column":1}},"children":[{"type":"text","value":"Tools/Resources","position":{"start":{"line":1,"column":1},"end":{"line":1,"column":1}},"key":"W8BOzEhwQg"}],"identifier":"tools-resources","label":"Tools/Resources","html_id":"tools-resources","implicit":true,"key":"cC4w5YNf17"},{"type":"list","ordered":false,"spread":false,"position":{"start":{"line":3,"column":1},"end":{"line":14,"column":1}},"children":[{"type":"listItem","spread":true,"position":{"start":{"line":3,"column":1},"end":{"line":6,"column":1}},"children":[{"type":"text","value":"Core textbooks","position":{"start":{"line":3,"column":1},"end":{"line":3,"column":1}},"key":"JiI34b4GZ1"},{"type":"list","ordered":true,"start":1,"spread":false,"position":{"start":{"line":4,"column":1},"end":{"line":5,"column":1}},"children":[{"type":"listItem","spread":true,"position":{"start":{"line":4,"column":1},"end":{"line":4,"column":1}},"children":[{"type":"link","url":"https://www.cs.cornell.edu/home/kleinber/networks-book/","position":{"start":{"line":4,"column":1},"end":{"line":4,"column":1}},"children":[{"type":"text","value":"Networks, Crowds, and Markets","position":{"start":{"line":4,"column":1},"end":{"line":4,"column":1}},"key":"bEGdkoAvq7"}],"urlSource":"https://www.cs.cornell.edu/home/kleinber/networks-book/","key":"d6j9VDpU0L"},{"type":"text","value":" by David Easley and Jon Kleinberg","position":{"start":{"line":4,"column":1},"end":{"line":4,"column":1}},"key":"ui9muZ97sj"}],"key":"QKavX47x8c"},{"type":"listItem","spread":true,"position":{"start":{"line":5,"column":1},"end":{"line":5,"column":1}},"children":[{"type":"link","url":"https://networks.quantecon.org/","position":{"start":{"line":5,"column":1},"end":{"line":5,"column":1}},"children":[{"type":"text","value":"Economics Networks","position":{"start":{"line":5,"column":1},"end":{"line":5,"column":1}},"key":"sWaq0LuzhZ"}],"urlSource":"https://networks.quantecon.org/","key":"oxjFndXAB9"},{"type":"text","value":" by John Stachurski and Thomas Sargent","position":{"start":{"line":5,"column":1},"end":{"line":5,"column":1}},"key":"acDjRjLXT7"}],"key":"IQquJSkkcb"}],"key":"yrB63W0BNQ"},{"type":"list","ordered":false,"spread":false,"position":{"start":{"line":6,"column":1},"end":{"line":6,"column":1}},"children":[{"type":"listItem","spread":true,"position":{"start":{"line":6,"column":1},"end":{"line":6,"column":1}},"children":[{"type":"text","value":"Will be supplemented by lecture notes for more computational content","position":{"start":{"line":6,"column":1},"end":{"line":6,"column":1}},"key":"TXXohN1Jxp"}],"key":"T6dUM8NzF2"}],"key":"drz69yMSi0"}],"key":"e2kmdPDdwS"},{"type":"listItem","spread":true,"position":{"start":{"line":7,"column":1},"end":{"line":7,"column":1}},"children":[{"type":"link","url":"https://julialang.org/","position":{"start":{"line":7,"column":1},"end":{"line":7,"column":1}},"children":[{"type":"text","value":"Julia","position":{"start":{"line":7,"column":1},"end":{"line":7,"column":1}},"key":"V3p3s2SjYM"}],"urlSource":"https://julialang.org/","key":"uJCyCxVwcL"},{"type":"text","value":" Programming language","position":{"start":{"line":7,"column":1},"end":{"line":7,"column":1}},"key":"zBQcK7M4uO"}],"key":"sWirjkQBxP"},{"type":"listItem","spread":true,"position":{"start":{"line":8,"column":1},"end":{"line":8,"column":1}},"children":[{"type":"text","value":"Lecture notes are accessible via the ","position":{"start":{"line":8,"column":1},"end":{"line":8,"column":1}},"key":"dHxHCHwAdL"},{"type":"link","url":"https://ucf-cap-6318.spencerlyon.com/","position":{"start":{"line":8,"column":1},"end":{"line":8,"column":1}},"children":[{"type":"text","value":"course website","position":{"start":{"line":8,"column":1},"end":{"line":8,"column":1}},"key":"O5Nhnk4OAe"}],"urlSource":"https://ucf-cap-6318.spencerlyon.com/","key":"a9bEks344E"}],"key":"S16dQdKrgG"},{"type":"listItem","spread":true,"position":{"start":{"line":9,"column":1},"end":{"line":9,"column":1}},"children":[{"type":"text","value":"Lecture notes AND assignments in Jupyter notebooks","position":{"start":{"line":9,"column":1},"end":{"line":9,"column":1}},"key":"IZzOivB1J7"}],"key":"sVjmDFNaHv"},{"type":"listItem","spread":true,"position":{"start":{"line":10,"column":1},"end":{"line":13,"column":1}},"children":[{"type":"text","value":"All course administration will happen through webcourses (Canvas)","position":{"start":{"line":10,"column":1},"end":{"line":10,"column":1}},"key":"DzbPEsq6OH"},{"type":"list","ordered":false,"spread":false,"position":{"start":{"line":11,"column":1},"end":{"line":13,"column":1}},"children":[{"type":"listItem","spread":true,"position":{"start":{"line":11,"column":1},"end":{"line":11,"column":1}},"children":[{"type":"text","value":"Assignments ","position":{"start":{"line":11,"column":1},"end":{"line":11,"column":1}},"key":"casv44dBmS"},{"type":"inlineCode","value":"me <-> you","position":{"start":{"line":11,"column":1},"end":{"line":11,"column":1}},"key":"Y5LyB6E1xY"}],"key":"P0M4LM0Crs"},{"type":"listItem","spread":true,"position":{"start":{"line":12,"column":1},"end":{"line":12,"column":1}},"children":[{"type":"text","value":"Feedback on assignments ","position":{"start":{"line":12,"column":1},"end":{"line":12,"column":1}},"key":"irMo5cJvDH"},{"type":"inlineCode","value":"me -> you","position":{"start":{"line":12,"column":1},"end":{"line":12,"column":1}},"key":"lIJ7W6tx3U"}],"key":"RLEFAXG8ZO"},{"type":"listItem","spread":true,"position":{"start":{"line":13,"column":1},"end":{"line":13,"column":1}},"children":[{"type":"text","value":"Discussion ","position":{"start":{"line":13,"column":1},"end":{"line":13,"column":1}},"key":"wsOdEbcXOZ"},{"type":"inlineCode","value":"me + you <-> me + you","position":{"start":{"line":13,"column":1},"end":{"line":13,"column":1}},"key":"c7zDyhVlHR"}],"key":"D1xCEiIGUv"}],"key":"tOi518HdPB"}],"key":"hmBwQVTpDY"},{"type":"listItem","spread":true,"position":{"start":{"line":14,"column":1},"end":{"line":14,"column":1}},"children":[{"type":"text","value":"Official grades will be visible on canvas","position":{"start":{"line":14,"column":1},"end":{"line":14,"column":1}},"key":"BA4IJ9159a"}],"key":"mmlOoSSl8u"}],"key":"DLHTWxVv9M"}],"visibility":"show","key":"I3CYAIKBgF"}],"key":"xVF1K47z3d"},"references":{"cite":{"order":[],"data":{}}},"footer":{"navigation":{"next":{"title":"Julia Setup","url":"/l01-02-setup","group":"Julia 1"}}},"domain":"http://localhost:3000"}