{"version":2,"kind":"Notebook","sha256":"5083d7da89fe636f343031df3319a9c7ba911ced69cff07cc0ad88d09d57cca4","slug":"l04-03-structural-balance","location":"/week04/L04.03_structural_balance.ipynb","dependencies":[],"frontmatter":{"title":"Structural Balance","content_includes_title":false,"kernelspec":{"name":"julia-1.10","display_name":"Julia 1.10.4","language":"julia"},"authors":[{"nameParsed":{"literal":"Spencer Lyon","given":"Spencer","family":"Lyon"},"name":"Spencer Lyon","orcid":"0009-0001-6461-885X","email":"spencer.lyon@ucf.edu","affiliations":["University of Central Florida","Valorum Data"],"id":"contributors-myst-generated-uid-0","corresponding":true}],"affiliations":[{"id":"University of Central Florida","name":"University of Central Florida"},{"id":"Valorum Data","name":"Valorum Data"}],"numbering":{"title":{"offset":1}},"thumbnail":"/build/e8165665e7da5ff6c9050aa529f882e5.png","thumbnailOptimized":"/build/e8165665e7da5ff6c9050aa529f882e5.webp","exports":[{"format":"ipynb","filename":"L04.03_structural_balance.ipynb","url":"/build/L04.03_structural_ba-62b6768549f84641d0c193adac6aed53.ipynb"}]},"widgets":{},"mdast":{"type":"root","children":[{"type":"block","kind":"notebook-content","data":{"slideshow":{"slide_type":"slide"},"tags":[]},"children":[{"type":"paragraph","position":{"start":{"line":3,"column":1},"end":{"line":3,"column":1}},"children":[{"type":"strong","position":{"start":{"line":3,"column":1},"end":{"line":3,"column":1}},"children":[{"type":"text","value":"Prerequisites","position":{"start":{"line":3,"column":1},"end":{"line":3,"column":1}},"key":"KpPcBG99gT"}],"key":"oi6uIR12VL"}],"key":"E9agOKkFmB"},{"type":"list","ordered":false,"spread":false,"position":{"start":{"line":5,"column":1},"end":{"line":8,"column":1}},"children":[{"type":"listItem","spread":true,"position":{"start":{"line":5,"column":1},"end":{"line":5,"column":1}},"children":[{"type":"text","value":"Introduction to Graphs","position":{"start":{"line":5,"column":1},"end":{"line":5,"column":1}},"key":"G5G7cSilJj"}],"key":"VqY7pBgYOD"},{"type":"listItem","spread":true,"position":{"start":{"line":6,"column":1},"end":{"line":6,"column":1}},"children":[{"type":"text","value":"Strong and Weak Ties","position":{"start":{"line":6,"column":1},"end":{"line":6,"column":1}},"key":"gAtsu4NwSW"}],"key":"MAbol6rlvV"},{"type":"listItem","spread":true,"position":{"start":{"line":7,"column":1},"end":{"line":8,"column":1}},"children":[{"type":"text","value":"Weighted Graphs","position":{"start":{"line":7,"column":1},"end":{"line":7,"column":1}},"key":"CUVJ2zXgrE"}],"key":"k2XZ5p63qu"}],"key":"w87pd9ux1e"},{"type":"paragraph","position":{"start":{"line":9,"column":1},"end":{"line":9,"column":1}},"children":[{"type":"strong","position":{"start":{"line":9,"column":1},"end":{"line":9,"column":1}},"children":[{"type":"text","value":"Outcomes","position":{"start":{"line":9,"column":1},"end":{"line":9,"column":1}},"key":"plnCrwM9DF"}],"key":"vBON5pWoSr"}],"key":"UwwZ714WMw"},{"type":"list","ordered":false,"spread":false,"position":{"start":{"line":11,"column":1},"end":{"line":14,"column":1}},"children":[{"type":"listItem","spread":true,"position":{"start":{"line":11,"column":1},"end":{"line":11,"column":1}},"children":[{"type":"text","value":"Understand the structural balance property for sets of three nodes","position":{"start":{"line":11,"column":1},"end":{"line":11,"column":1}},"key":"HT79PcudBi"}],"key":"Yt54u4Ss1W"},{"type":"listItem","spread":true,"position":{"start":{"line":12,"column":1},"end":{"line":12,"column":1}},"children":[{"type":"text","value":"Understand the structural balance theorem for a graph","position":{"start":{"line":12,"column":1},"end":{"line":12,"column":1}},"key":"psHuE5jCYt"}],"key":"ammpYuMKp7"},{"type":"listItem","spread":true,"position":{"start":{"line":13,"column":1},"end":{"line":14,"column":1}},"children":[{"type":"text","value":"Recognize structural balance in a weighted graph","position":{"start":{"line":13,"column":1},"end":{"line":13,"column":1}},"key":"WlVdDgJdc3"}],"key":"no331XFuUq"}],"key":"xSIGv0A7cm"},{"type":"paragraph","position":{"start":{"line":15,"column":1},"end":{"line":15,"column":1}},"children":[{"type":"strong","position":{"start":{"line":15,"column":1},"end":{"line":15,"column":1}},"children":[{"type":"text","value":"References","position":{"start":{"line":15,"column":1},"end":{"line":15,"column":1}},"key":"okqGG9Dv9K"}],"key":"bClIm2rYYX"}],"key":"hWPDkBkYW8"},{"type":"list","ordered":false,"spread":false,"position":{"start":{"line":17,"column":1},"end":{"line":17,"column":1}},"children":[{"type":"listItem","spread":true,"position":{"start":{"line":17,"column":1},"end":{"line":17,"column":1}},"children":[{"type":"link","url":"https://www.cs.cornell.edu/home/kleinber/networks-book/","position":{"start":{"line":17,"column":1},"end":{"line":17,"column":1}},"children":[{"type":"text","value":"Easley and Kleinberg","position":{"start":{"line":17,"column":1},"end":{"line":17,"column":1}},"key":"Kes7s3ewgx"}],"urlSource":"https://www.cs.cornell.edu/home/kleinber/networks-book/","key":"Lt6Qiw37ou"},{"type":"text","value":" chapter 5 (especially section 5.1-5-3)","position":{"start":{"line":17,"column":1},"end":{"line":17,"column":1}},"key":"kRCwf4vR5v"}],"key":"tchVfssZVS"}],"key":"kff4vQ1MDy"}],"visibility":"show","key":"YozkLt6j0w"},{"type":"block","kind":"notebook-content","data":{"slideshow":{"slide_type":"slide"},"tags":[]},"children":[{"type":"heading","depth":2,"position":{"start":{"line":1,"column":1},"end":{"line":1,"column":1}},"children":[{"type":"text","value":"Introduction","position":{"start":{"line":1,"column":1},"end":{"line":1,"column":1}},"key":"YB6YkYY34D"}],"identifier":"introduction","label":"Introduction","html_id":"introduction","implicit":true,"key":"NXeADNy7bv"},{"type":"list","ordered":false,"spread":false,"position":{"start":{"line":3,"column":1},"end":{"line":9,"column":1}},"children":[{"type":"listItem","spread":true,"position":{"start":{"line":3,"column":1},"end":{"line":3,"column":1}},"children":[{"type":"text","value":"We now shift our discussion to the notion of whether or not a network is balanced","position":{"start":{"line":3,"column":1},"end":{"line":3,"column":1}},"key":"WiUgctn3ue"}],"key":"fXlZvkcQIO"},{"type":"listItem","spread":true,"position":{"start":{"line":4,"column":1},"end":{"line":7,"column":1}},"children":[{"type":"text","value":"For this discussion we will use weighted graphs, where weights are one of","position":{"start":{"line":4,"column":1},"end":{"line":4,"column":1}},"key":"Sybm14idun"},{"type":"list","ordered":false,"spread":false,"position":{"start":{"line":5,"column":1},"end":{"line":7,"column":1}},"children":[{"type":"listItem","spread":true,"position":{"start":{"line":5,"column":1},"end":{"line":5,"column":1}},"children":[{"type":"text","value":"1: if nodes are friends (also called ","position":{"start":{"line":5,"column":1},"end":{"line":5,"column":1}},"key":"IMWmc4T0wQ"},{"type":"inlineCode","value":"+","position":{"start":{"line":5,"column":1},"end":{"line":5,"column":1}},"key":"XrS7bsAlZA"},{"type":"text","value":")","position":{"start":{"line":5,"column":1},"end":{"line":5,"column":1}},"key":"lSymphKAG9"}],"key":"gYXkuP93Qx"},{"type":"listItem","spread":true,"position":{"start":{"line":6,"column":1},"end":{"line":6,"column":1}},"children":[{"type":"text","value":"0: if they don’t know eachother","position":{"start":{"line":6,"column":1},"end":{"line":6,"column":1}},"key":"VeGPi02We5"}],"key":"dEkXJplzrh"},{"type":"listItem","spread":true,"position":{"start":{"line":7,"column":1},"end":{"line":7,"column":1}},"children":[{"type":"text","value":"-1: if nodes are enemies (also called ","position":{"start":{"line":7,"column":1},"end":{"line":7,"column":1}},"key":"reACOj1s8n"},{"type":"inlineCode","value":"-","position":{"start":{"line":7,"column":1},"end":{"line":7,"column":1}},"key":"LcPN2xnXgq"},{"type":"text","value":")","position":{"start":{"line":7,"column":1},"end":{"line":7,"column":1}},"key":"S71yQkpJ3W"}],"key":"fhRKMO2orL"}],"key":"n3XG6vqWJ6"}],"key":"pe8YY8aUEY"},{"type":"listItem","spread":true,"position":{"start":{"line":8,"column":1},"end":{"line":8,"column":1}},"children":[{"type":"text","value":"We won’t consider strength of ties right now","position":{"start":{"line":8,"column":1},"end":{"line":8,"column":1}},"key":"WDs2FfPfUw"}],"key":"fAc9X872Ry"},{"type":"listItem","spread":true,"position":{"start":{"line":9,"column":1},"end":{"line":9,"column":1}},"children":[{"type":"text","value":"We will also limit discussion to complete graphs (cliques) where all nodes are connected to all other nodes","position":{"start":{"line":9,"column":1},"end":{"line":9,"column":1}},"key":"kjyYmF6RzM"}],"key":"qKMmjewUH4"}],"key":"zOy4DOOsUR"}],"visibility":"show","key":"C3YqtAJ5Qy"},{"type":"block","kind":"notebook-content","data":{"slideshow":{"slide_type":"subslide"},"tags":[]},"children":[{"type":"heading","depth":2,"position":{"start":{"line":1,"column":1},"end":{"line":1,"column":1}},"children":[{"type":"text","value":"Balance in Triangles","position":{"start":{"line":1,"column":1},"end":{"line":1,"column":1}},"key":"xI2hfRLAoT"}],"identifier":"balance-in-triangles","label":"Balance in Triangles","html_id":"balance-in-triangles","implicit":true,"key":"nCUzkE6ixJ"},{"type":"list","ordered":false,"spread":false,"position":{"start":{"line":3,"column":1},"end":{"line":4,"column":1}},"children":[{"type":"listItem","spread":true,"position":{"start":{"line":3,"column":1},"end":{"line":3,"column":1}},"children":[{"type":"text","value":"To start thinking about balance, consider the possible configurations of ","position":{"start":{"line":3,"column":1},"end":{"line":3,"column":1}},"key":"VS6HBZ8cRG"},{"type":"inlineCode","value":"+","position":{"start":{"line":3,"column":1},"end":{"line":3,"column":1}},"key":"Oec2g5j7g7"},{"type":"text","value":" and ","position":{"start":{"line":3,"column":1},"end":{"line":3,"column":1}},"key":"SGNwNeJ3jw"},{"type":"inlineCode","value":"-","position":{"start":{"line":3,"column":1},"end":{"line":3,"column":1}},"key":"XF1aU6QERy"},{"type":"text","value":" edges in a triangle","position":{"start":{"line":3,"column":1},"end":{"line":3,"column":1}},"key":"EvGcogyD2Q"}],"key":"sFf45N7CFK"},{"type":"listItem","spread":true,"position":{"start":{"line":4,"column":1},"end":{"line":4,"column":1}},"children":[{"type":"text","value":"There are 4 options as shown below","position":{"start":{"line":4,"column":1},"end":{"line":4,"column":1}},"key":"okK1IB4me5"}],"key":"e9wKJmyQdh"}],"key":"B5nPtBP7x0"}],"visibility":"show","key":"dKAxZ8oZk1"},{"type":"block","kind":"notebook-content","children":[{"type":"image","url":"/build/e8165665e7da5ff6c9050aa529f882e5.png","alt":"https://compsosci-resources.s3.amazonaws.com/graph-theory-lectures/images/balance_in_triangles.png","position":{"start":{"line":1,"column":1},"end":{"line":1,"column":1}},"key":"DZtfTawciY","urlSource":"https://compsosci-resources.s3.amazonaws.com/graph-theory-lectures/images/balance_in_triangles.png","urlOptimized":"/build/e8165665e7da5ff6c9050aa529f882e5.webp"}],"key":"HXaERyYXo2"},{"type":"block","kind":"notebook-content","children":[{"type":"list","ordered":false,"spread":false,"position":{"start":{"line":1,"column":1},"end":{"line":4,"column":1}},"children":[{"type":"listItem","spread":true,"position":{"start":{"line":1,"column":1},"end":{"line":1,"column":1}},"children":[{"type":"text","value":"In (a) all people are friends -- this is happy and balanced","position":{"start":{"line":1,"column":1},"end":{"line":1,"column":1}},"key":"raiyGDBiqA"}],"key":"kvCt5EyKSV"},{"type":"listItem","spread":true,"position":{"start":{"line":2,"column":1},"end":{"line":2,"column":1}},"children":[{"type":"text","value":"In (c) A-B are friends with a common enemy C -- nobody has reason to change alliances => balanced","position":{"start":{"line":2,"column":1},"end":{"line":2,"column":1}},"key":"Du2CV6bxPG"}],"key":"pgJkL5cX8i"},{"type":"listItem","spread":true,"position":{"start":{"line":3,"column":1},"end":{"line":3,"column":1}},"children":[{"type":"text","value":"In (b) A is friends with B and C, but they are enemies -- B and C may try to flip A against other => not balanced","position":{"start":{"line":3,"column":1},"end":{"line":3,"column":1}},"key":"nF5qwFqdQQ"}],"key":"th74gkxhd2"},{"type":"listItem","spread":true,"position":{"start":{"line":4,"column":1},"end":{"line":4,"column":1}},"children":[{"type":"text","value":"In (d) all are enemies -- two parties have incentive to team up against common enemy => not balanced","position":{"start":{"line":4,"column":1},"end":{"line":4,"column":1}},"key":"lyGnh7k5Kc"}],"key":"NDHeQktyBe"}],"key":"IBtUZL4sgm"}],"key":"RKcI5jzIz7"},{"type":"block","kind":"notebook-content","data":{"slideshow":{"slide_type":"slide"},"tags":[]},"children":[{"type":"heading","depth":2,"position":{"start":{"line":1,"column":1},"end":{"line":1,"column":1}},"children":[{"type":"text","value":"Balance In Graphs","position":{"start":{"line":1,"column":1},"end":{"line":1,"column":1}},"key":"oP4Eno3GcB"}],"identifier":"balance-in-graphs","label":"Balance In Graphs","html_id":"balance-in-graphs","implicit":true,"key":"pb2h5xpSnX"},{"type":"list","ordered":false,"spread":false,"position":{"start":{"line":3,"column":1},"end":{"line":4,"column":1}},"children":[{"type":"listItem","spread":true,"position":{"start":{"line":3,"column":1},"end":{"line":3,"column":1}},"children":[{"type":"text","value":"This definition of balance in triangles can be extended to graphs","position":{"start":{"line":3,"column":1},"end":{"line":3,"column":1}},"key":"pVBiaLJthv"}],"key":"MlKbUs1bNE"},{"type":"listItem","spread":true,"position":{"start":{"line":4,"column":1},"end":{"line":4,"column":1}},"children":[{"type":"text","value":"A complete graph G satisfies the ","position":{"start":{"line":4,"column":1},"end":{"line":4,"column":1}},"key":"ZaQFbp1km5"},{"type":"strong","position":{"start":{"line":4,"column":1},"end":{"line":4,"column":1}},"children":[{"type":"text","value":"Structural Balance Property","position":{"start":{"line":4,"column":1},"end":{"line":4,"column":1}},"key":"TMZ6MSos9N"}],"key":"pLDeqQI4tu"},{"type":"text","value":" if for ","position":{"start":{"line":4,"column":1},"end":{"line":4,"column":1}},"key":"UEGNW6ILTp"},{"type":"emphasis","position":{"start":{"line":4,"column":1},"end":{"line":4,"column":1}},"children":[{"type":"text","value":"every","position":{"start":{"line":4,"column":1},"end":{"line":4,"column":1}},"key":"YmBSavl5ib"}],"key":"nA5x9QwbcF"},{"type":"text","value":" set of three nodes, exactly one or three of the edges is labeled ","position":{"start":{"line":4,"column":1},"end":{"line":4,"column":1}},"key":"jNZbymNino"},{"type":"inlineCode","value":"+","position":{"start":{"line":4,"column":1},"end":{"line":4,"column":1}},"key":"ZEDR744y42"}],"key":"D5hYIirbs5"}],"key":"UDpejXVb1X"}],"visibility":"show","key":"VZ80XlZrpt"},{"type":"block","kind":"notebook-content","data":{"slideshow":{"slide_type":"subslide"},"tags":[]},"children":[{"type":"heading","depth":3,"position":{"start":{"line":1,"column":1},"end":{"line":1,"column":1}},"children":[{"type":"text","value":"Implications: Balance Theorem","position":{"start":{"line":1,"column":1},"end":{"line":1,"column":1}},"key":"qyk2TsS5th"}],"identifier":"implications-balance-theorem","label":"Implications: Balance Theorem","html_id":"implications-balance-theorem","implicit":true,"key":"AN6sdSuQNr"},{"type":"list","ordered":false,"spread":false,"position":{"start":{"line":3,"column":1},"end":{"line":3,"column":1}},"children":[{"type":"listItem","spread":true,"position":{"start":{"line":3,"column":1},"end":{"line":3,"column":1}},"children":[{"type":"text","value":"One implication of the Structural Balance Property is the ","position":{"start":{"line":3,"column":1},"end":{"line":3,"column":1}},"key":"t9lzmDB1ul"},{"type":"strong","position":{"start":{"line":3,"column":1},"end":{"line":3,"column":1}},"children":[{"type":"text","value":"Balance Theorem","position":{"start":{"line":3,"column":1},"end":{"line":3,"column":1}},"key":"d9zumP5jrz"}],"key":"uoYLBrW8In"}],"key":"JwtlyG3f2d"}],"key":"ILzFlPxxN4"},{"type":"blockquote","position":{"start":{"line":4,"column":1},"end":{"line":4,"column":1}},"children":[{"type":"paragraph","position":{"start":{"line":4,"column":1},"end":{"line":4,"column":1}},"children":[{"type":"text","value":"If a labeled complete graph is balanced, then either all pairs of nodes are friends, or else the nodes can be divided into two groups, X and Y , such that every pair of nodes in X like each other, every pair of nodes in Y like each other, and everyone in X is the enemy of everyone in Y .","position":{"start":{"line":4,"column":1},"end":{"line":4,"column":1}},"key":"f6Z3XNO9MY"}],"key":"BUethmEps2"}],"key":"WlNIGlM2tf"},{"type":"list","ordered":false,"spread":false,"position":{"start":{"line":5,"column":1},"end":{"line":5,"column":1}},"children":[{"type":"listItem","spread":true,"position":{"start":{"line":5,"column":1},"end":{"line":5,"column":1}},"children":[{"type":"text","value":"Notice the strength of the statement: either all ","position":{"start":{"line":5,"column":1},"end":{"line":5,"column":1}},"key":"alRY6qlkHA"},{"type":"inlineCode","value":"+","position":{"start":{"line":5,"column":1},"end":{"line":5,"column":1}},"key":"AM7g8IVgdh"},{"type":"text","value":" or two mutually exclusive groups of friends that are all enemies with other group","position":{"start":{"line":5,"column":1},"end":{"line":5,"column":1}},"key":"wZM9jBtOwh"}],"key":"UJoUuzc3Cl"}],"key":"LVktcUrIlS"}],"visibility":"show","key":"XIPNZ4P2Yv"},{"type":"block","kind":"notebook-content","data":{"slideshow":{"slide_type":"subslide"},"tags":[]},"children":[{"type":"heading","depth":3,"position":{"start":{"line":1,"column":1},"end":{"line":1,"column":1}},"children":[{"type":"text","value":"Proving Balance Theorem","position":{"start":{"line":1,"column":1},"end":{"line":1,"column":1}},"key":"VikeuzF2rt"}],"identifier":"proving-balance-theorem","label":"Proving Balance Theorem","html_id":"proving-balance-theorem","implicit":true,"key":"Jf5ggAarVL"},{"type":"list","ordered":false,"spread":false,"position":{"start":{"line":3,"column":1},"end":{"line":11,"column":1}},"children":[{"type":"listItem","spread":true,"position":{"start":{"line":3,"column":1},"end":{"line":3,"column":1}},"children":[{"type":"text","value":"We will provide some intuition for how to prove the Balance Theorem, which will help us understand why it is true","position":{"start":{"line":3,"column":1},"end":{"line":3,"column":1}},"key":"GTQqu3SY5f"}],"key":"K9TyoJCESQ"},{"type":"listItem","spread":true,"position":{"start":{"line":4,"column":1},"end":{"line":4,"column":1}},"children":[{"type":"text","value":"Consider a complete Graph ","position":{"start":{"line":4,"column":1},"end":{"line":4,"column":1}},"key":"eZcISSQupb"},{"type":"inlineCode","value":"G","position":{"start":{"line":4,"column":1},"end":{"line":4,"column":1}},"key":"me1zlHflK3"}],"key":"trqmOasmhZ"},{"type":"listItem","spread":true,"position":{"start":{"line":5,"column":1},"end":{"line":7,"column":1}},"children":[{"type":"text","value":"Two alternative cases:","position":{"start":{"line":5,"column":1},"end":{"line":5,"column":1}},"key":"TrI3yHLdnI"},{"type":"list","ordered":true,"start":1,"spread":false,"position":{"start":{"line":6,"column":1},"end":{"line":7,"column":1}},"children":[{"type":"listItem","spread":true,"position":{"start":{"line":6,"column":1},"end":{"line":6,"column":1}},"children":[{"type":"text","value":"Everyone is friends: satisfies theorem by definition","position":{"start":{"line":6,"column":1},"end":{"line":6,"column":1}},"key":"In2Smnuu54"}],"key":"zdMyikAMgw"},{"type":"listItem","spread":true,"position":{"start":{"line":7,"column":1},"end":{"line":7,"column":1}},"children":[{"type":"text","value":"There are some ","position":{"start":{"line":7,"column":1},"end":{"line":7,"column":1}},"key":"C6zbw50zvI"},{"type":"inlineCode","value":"+","position":{"start":{"line":7,"column":1},"end":{"line":7,"column":1}},"key":"uCHXzjgNHa"},{"type":"text","value":" and some ","position":{"start":{"line":7,"column":1},"end":{"line":7,"column":1}},"key":"ZPAcTByNpG"},{"type":"inlineCode","value":"-","position":{"start":{"line":7,"column":1},"end":{"line":7,"column":1}},"key":"hAo4nW3zQt"},{"type":"text","value":" edges: need to prove","position":{"start":{"line":7,"column":1},"end":{"line":7,"column":1}},"key":"jupCvWA7jB"}],"key":"Zs2SHtyTN6"}],"key":"irVPEvoBzl"}],"key":"LhfTPYah3c"},{"type":"listItem","spread":true,"position":{"start":{"line":8,"column":1},"end":{"line":11,"column":1}},"children":[{"type":"text","value":"For case 2, we must be able to split G into ","position":{"start":{"line":8,"column":1},"end":{"line":8,"column":1}},"key":"Sxy4Clzj5S"},{"type":"inlineMath","value":"X","position":{"start":{"line":8,"column":1},"end":{"line":8,"column":1}},"html":"<span class=\"katex\"><span class=\"katex-mathml\"><math xmlns=\"http://www.w3.org/1998/Math/MathML\"><semantics><mrow><mi>X</mi></mrow><annotation encoding=\"application/x-tex\">X</annotation></semantics></math></span><span class=\"katex-html\" aria-hidden=\"true\"><span class=\"base\"><span class=\"strut\" style=\"height:0.6833em;\"></span><span class=\"mord mathnormal\" style=\"margin-right:0.07847em;\">X</span></span></span></span>","key":"hpTenVrVza"},{"type":"text","value":" and ","position":{"start":{"line":8,"column":1},"end":{"line":8,"column":1}},"key":"OdIwZrbhl2"},{"type":"inlineMath","value":"Y","position":{"start":{"line":8,"column":1},"end":{"line":8,"column":1}},"html":"<span class=\"katex\"><span class=\"katex-mathml\"><math xmlns=\"http://www.w3.org/1998/Math/MathML\"><semantics><mrow><mi>Y</mi></mrow><annotation encoding=\"application/x-tex\">Y</annotation></semantics></math></span><span class=\"katex-html\" aria-hidden=\"true\"><span class=\"base\"><span class=\"strut\" style=\"height:0.6833em;\"></span><span class=\"mord mathnormal\" style=\"margin-right:0.22222em;\">Y</span></span></span></span>","key":"W46nG71X4z"},{"type":"text","value":" where the following hold","position":{"start":{"line":8,"column":1},"end":{"line":8,"column":1}},"key":"bFjEH15G2H"},{"type":"list","ordered":true,"start":1,"spread":false,"position":{"start":{"line":9,"column":1},"end":{"line":11,"column":1}},"children":[{"type":"listItem","spread":true,"position":{"start":{"line":9,"column":1},"end":{"line":9,"column":1}},"children":[{"type":"text","value":"Every node in ","position":{"start":{"line":9,"column":1},"end":{"line":9,"column":1}},"key":"KMBBw1DvHm"},{"type":"inlineMath","value":"X","position":{"start":{"line":9,"column":1},"end":{"line":9,"column":1}},"html":"<span class=\"katex\"><span class=\"katex-mathml\"><math xmlns=\"http://www.w3.org/1998/Math/MathML\"><semantics><mrow><mi>X</mi></mrow><annotation encoding=\"application/x-tex\">X</annotation></semantics></math></span><span class=\"katex-html\" aria-hidden=\"true\"><span class=\"base\"><span class=\"strut\" style=\"height:0.6833em;\"></span><span class=\"mord mathnormal\" style=\"margin-right:0.07847em;\">X</span></span></span></span>","key":"lYcNNDH1iV"},{"type":"text","value":" is friends with every other node in ","position":{"start":{"line":9,"column":1},"end":{"line":9,"column":1}},"key":"DSztmhvuKW"},{"type":"inlineMath","value":"X","position":{"start":{"line":9,"column":1},"end":{"line":9,"column":1}},"html":"<span class=\"katex\"><span class=\"katex-mathml\"><math xmlns=\"http://www.w3.org/1998/Math/MathML\"><semantics><mrow><mi>X</mi></mrow><annotation encoding=\"application/x-tex\">X</annotation></semantics></math></span><span class=\"katex-html\" aria-hidden=\"true\"><span class=\"base\"><span class=\"strut\" style=\"height:0.6833em;\"></span><span class=\"mord mathnormal\" style=\"margin-right:0.07847em;\">X</span></span></span></span>","key":"RwlfflKMNw"}],"key":"k2G0WlqOGv"},{"type":"listItem","spread":true,"position":{"start":{"line":10,"column":1},"end":{"line":10,"column":1}},"children":[{"type":"text","value":"Every node in ","position":{"start":{"line":10,"column":1},"end":{"line":10,"column":1}},"key":"dI8UZyoYus"},{"type":"inlineMath","value":"Y","position":{"start":{"line":10,"column":1},"end":{"line":10,"column":1}},"html":"<span class=\"katex\"><span class=\"katex-mathml\"><math xmlns=\"http://www.w3.org/1998/Math/MathML\"><semantics><mrow><mi>Y</mi></mrow><annotation encoding=\"application/x-tex\">Y</annotation></semantics></math></span><span class=\"katex-html\" aria-hidden=\"true\"><span class=\"base\"><span class=\"strut\" style=\"height:0.6833em;\"></span><span class=\"mord mathnormal\" style=\"margin-right:0.22222em;\">Y</span></span></span></span>","key":"eIrjNtATHn"},{"type":"text","value":" is friends with every other node in ","position":{"start":{"line":10,"column":1},"end":{"line":10,"column":1}},"key":"yvCgrlYklO"},{"type":"inlineMath","value":"Y","position":{"start":{"line":10,"column":1},"end":{"line":10,"column":1}},"html":"<span class=\"katex\"><span class=\"katex-mathml\"><math xmlns=\"http://www.w3.org/1998/Math/MathML\"><semantics><mrow><mi>Y</mi></mrow><annotation encoding=\"application/x-tex\">Y</annotation></semantics></math></span><span class=\"katex-html\" aria-hidden=\"true\"><span class=\"base\"><span class=\"strut\" style=\"height:0.6833em;\"></span><span class=\"mord mathnormal\" style=\"margin-right:0.22222em;\">Y</span></span></span></span>","key":"oUZX77L653"}],"key":"AqgiERWofa"},{"type":"listItem","spread":true,"position":{"start":{"line":11,"column":1},"end":{"line":11,"column":1}},"children":[{"type":"text","value":"Every node in ","position":{"start":{"line":11,"column":1},"end":{"line":11,"column":1}},"key":"nKKi9JXdQ5"},{"type":"inlineMath","value":"X","position":{"start":{"line":11,"column":1},"end":{"line":11,"column":1}},"html":"<span class=\"katex\"><span class=\"katex-mathml\"><math xmlns=\"http://www.w3.org/1998/Math/MathML\"><semantics><mrow><mi>X</mi></mrow><annotation encoding=\"application/x-tex\">X</annotation></semantics></math></span><span class=\"katex-html\" aria-hidden=\"true\"><span class=\"base\"><span class=\"strut\" style=\"height:0.6833em;\"></span><span class=\"mord mathnormal\" style=\"margin-right:0.07847em;\">X</span></span></span></span>","key":"UjupkBwlZf"},{"type":"text","value":" is enemies with every node in ","position":{"start":{"line":11,"column":1},"end":{"line":11,"column":1}},"key":"dIH6ncTs87"},{"type":"inlineMath","value":"Y","position":{"start":{"line":11,"column":1},"end":{"line":11,"column":1}},"html":"<span class=\"katex\"><span class=\"katex-mathml\"><math xmlns=\"http://www.w3.org/1998/Math/MathML\"><semantics><mrow><mi>Y</mi></mrow><annotation encoding=\"application/x-tex\">Y</annotation></semantics></math></span><span class=\"katex-html\" aria-hidden=\"true\"><span class=\"base\"><span class=\"strut\" style=\"height:0.6833em;\"></span><span class=\"mord mathnormal\" style=\"margin-right:0.22222em;\">Y</span></span></span></span>","key":"YAy3a1i8T9"}],"key":"bQKA9maBra"}],"key":"A6v4TufiFL"}],"key":"bOkBg3rEVC"}],"key":"mZgMmZfXUm"}],"visibility":"show","key":"KS0ac93Y7e"},{"type":"block","kind":"notebook-content","data":{"slideshow":{"slide_type":"subslide"},"tags":[]},"children":[{"type":"heading","depth":3,"position":{"start":{"line":1,"column":1},"end":{"line":1,"column":1}},"children":[{"type":"text","value":"Proof by construction","position":{"start":{"line":1,"column":1},"end":{"line":1,"column":1}},"key":"x35pOihbyH"}],"identifier":"proof-by-construction","label":"Proof by construction","html_id":"proof-by-construction","implicit":true,"key":"kVrQMNkU8w"},{"type":"list","ordered":false,"spread":false,"position":{"start":{"line":3,"column":1},"end":{"line":7,"column":1}},"children":[{"type":"listItem","spread":true,"position":{"start":{"line":3,"column":1},"end":{"line":3,"column":1}},"children":[{"type":"text","value":"Start with complete, balanced graph ","position":{"start":{"line":3,"column":1},"end":{"line":3,"column":1}},"key":"W24NI4Z8s5"},{"type":"inlineMath","value":"G","position":{"start":{"line":3,"column":1},"end":{"line":3,"column":1}},"html":"<span class=\"katex\"><span class=\"katex-mathml\"><math xmlns=\"http://www.w3.org/1998/Math/MathML\"><semantics><mrow><mi>G</mi></mrow><annotation encoding=\"application/x-tex\">G</annotation></semantics></math></span><span class=\"katex-html\" aria-hidden=\"true\"><span class=\"base\"><span class=\"strut\" style=\"height:0.6833em;\"></span><span class=\"mord mathnormal\">G</span></span></span></span>","key":"CRITpYSLSc"},{"type":"text","value":" (our only assumption!)","position":{"start":{"line":3,"column":1},"end":{"line":3,"column":1}},"key":"AoOI2K9kF1"}],"key":"nEbW9LLdBy"},{"type":"listItem","spread":true,"position":{"start":{"line":4,"column":1},"end":{"line":4,"column":1}},"children":[{"type":"text","value":"We will prove the balance theorem by constructing sets ","position":{"start":{"line":4,"column":1},"end":{"line":4,"column":1}},"key":"F8NHy0H3B7"},{"type":"inlineMath","value":"X","position":{"start":{"line":4,"column":1},"end":{"line":4,"column":1}},"html":"<span class=\"katex\"><span class=\"katex-mathml\"><math xmlns=\"http://www.w3.org/1998/Math/MathML\"><semantics><mrow><mi>X</mi></mrow><annotation encoding=\"application/x-tex\">X</annotation></semantics></math></span><span class=\"katex-html\" aria-hidden=\"true\"><span class=\"base\"><span class=\"strut\" style=\"height:0.6833em;\"></span><span class=\"mord mathnormal\" style=\"margin-right:0.07847em;\">X</span></span></span></span>","key":"MppnIk7M3j"},{"type":"text","value":" and ","position":{"start":{"line":4,"column":1},"end":{"line":4,"column":1}},"key":"Pvc5xPgCy0"},{"type":"inlineMath","value":"Y","position":{"start":{"line":4,"column":1},"end":{"line":4,"column":1}},"html":"<span class=\"katex\"><span class=\"katex-mathml\"><math xmlns=\"http://www.w3.org/1998/Math/MathML\"><semantics><mrow><mi>Y</mi></mrow><annotation encoding=\"application/x-tex\">Y</annotation></semantics></math></span><span class=\"katex-html\" aria-hidden=\"true\"><span class=\"base\"><span class=\"strut\" style=\"height:0.6833em;\"></span><span class=\"mord mathnormal\" style=\"margin-right:0.22222em;\">Y</span></span></span></span>","key":"g0N1jYCEis"},{"type":"text","value":" and verifying that the members of these sets satisfy the 3 properties outlined above","position":{"start":{"line":4,"column":1},"end":{"line":4,"column":1}},"key":"fpgOaWX7OK"}],"key":"s8RWxAQBFh"},{"type":"listItem","spread":true,"position":{"start":{"line":5,"column":1},"end":{"line":5,"column":1}},"children":[{"type":"text","value":"To start, pick any node ","position":{"start":{"line":5,"column":1},"end":{"line":5,"column":1}},"key":"EJbUmNilhO"},{"type":"inlineMath","value":"A \\in G","position":{"start":{"line":5,"column":1},"end":{"line":5,"column":1}},"html":"<span class=\"katex\"><span class=\"katex-mathml\"><math xmlns=\"http://www.w3.org/1998/Math/MathML\"><semantics><mrow><mi>A</mi><mo>∈</mo><mi>G</mi></mrow><annotation encoding=\"application/x-tex\">A \\in G</annotation></semantics></math></span><span class=\"katex-html\" aria-hidden=\"true\"><span class=\"base\"><span class=\"strut\" style=\"height:0.7224em;vertical-align:-0.0391em;\"></span><span class=\"mord mathnormal\">A</span><span class=\"mspace\" style=\"margin-right:0.2778em;\"></span><span class=\"mrel\">∈</span><span class=\"mspace\" style=\"margin-right:0.2778em;\"></span></span><span class=\"base\"><span class=\"strut\" style=\"height:0.6833em;\"></span><span class=\"mord mathnormal\">G</span></span></span></span>","key":"Q6qmXyX59D"}],"key":"GPiL84Rpzw"},{"type":"listItem","spread":true,"position":{"start":{"line":6,"column":1},"end":{"line":6,"column":1}},"children":[{"type":"text","value":"Divide all other nodes that are friends with ","position":{"start":{"line":6,"column":1},"end":{"line":6,"column":1}},"key":"xW0By5LEKn"},{"type":"inlineMath","value":"A","position":{"start":{"line":6,"column":1},"end":{"line":6,"column":1}},"html":"<span class=\"katex\"><span class=\"katex-mathml\"><math xmlns=\"http://www.w3.org/1998/Math/MathML\"><semantics><mrow><mi>A</mi></mrow><annotation encoding=\"application/x-tex\">A</annotation></semantics></math></span><span class=\"katex-html\" aria-hidden=\"true\"><span class=\"base\"><span class=\"strut\" style=\"height:0.6833em;\"></span><span class=\"mord mathnormal\">A</span></span></span></span>","key":"InOPTUyv3l"},{"type":"text","value":" into ","position":{"start":{"line":6,"column":1},"end":{"line":6,"column":1}},"key":"jcWhiaMGUO"},{"type":"inlineMath","value":"X","position":{"start":{"line":6,"column":1},"end":{"line":6,"column":1}},"html":"<span class=\"katex\"><span class=\"katex-mathml\"><math xmlns=\"http://www.w3.org/1998/Math/MathML\"><semantics><mrow><mi>X</mi></mrow><annotation encoding=\"application/x-tex\">X</annotation></semantics></math></span><span class=\"katex-html\" aria-hidden=\"true\"><span class=\"base\"><span class=\"strut\" style=\"height:0.6833em;\"></span><span class=\"mord mathnormal\" style=\"margin-right:0.07847em;\">X</span></span></span></span>","key":"WWM0uHbVSe"},{"type":"text","value":" and enemies into ","position":{"start":{"line":6,"column":1},"end":{"line":6,"column":1}},"key":"tp1dp3tQ1i"},{"type":"inlineMath","value":"Y","position":{"start":{"line":6,"column":1},"end":{"line":6,"column":1}},"html":"<span class=\"katex\"><span class=\"katex-mathml\"><math xmlns=\"http://www.w3.org/1998/Math/MathML\"><semantics><mrow><mi>Y</mi></mrow><annotation encoding=\"application/x-tex\">Y</annotation></semantics></math></span><span class=\"katex-html\" aria-hidden=\"true\"><span class=\"base\"><span class=\"strut\" style=\"height:0.6833em;\"></span><span class=\"mord mathnormal\" style=\"margin-right:0.22222em;\">Y</span></span></span></span>","key":"TjE7WWgptp"}],"key":"nmowxFoVbr"},{"type":"listItem","spread":true,"position":{"start":{"line":7,"column":1},"end":{"line":7,"column":1}},"children":[{"type":"text","value":"Because ","position":{"start":{"line":7,"column":1},"end":{"line":7,"column":1}},"key":"jdUZr7LhuR"},{"type":"inlineMath","value":"G","position":{"start":{"line":7,"column":1},"end":{"line":7,"column":1}},"html":"<span class=\"katex\"><span class=\"katex-mathml\"><math xmlns=\"http://www.w3.org/1998/Math/MathML\"><semantics><mrow><mi>G</mi></mrow><annotation encoding=\"application/x-tex\">G</annotation></semantics></math></span><span class=\"katex-html\" aria-hidden=\"true\"><span class=\"base\"><span class=\"strut\" style=\"height:0.6833em;\"></span><span class=\"mord mathnormal\">G</span></span></span></span>","key":"Or5kgyYzbg"},{"type":"text","value":" is complete, this is all nodes","position":{"start":{"line":7,"column":1},"end":{"line":7,"column":1}},"key":"xxxeLOdeMh"}],"key":"QXtZx6Nbyy"}],"key":"wJXDv0nJOP"}],"visibility":"show","key":"xMMyWfeNzR"},{"type":"block","kind":"notebook-content","data":{"slideshow":{"slide_type":"fragment"},"tags":[]},"children":[{"type":"heading","depth":4,"position":{"start":{"line":1,"column":1},"end":{"line":1,"column":1}},"children":[{"type":"text","value":"Condition 1: ","position":{"start":{"line":1,"column":1},"end":{"line":1,"column":1}},"key":"zTDmiMbRhG"},{"type":"inlineMath","value":"\\forall B, C \\in X \\quad B \\rightarrow C = +","position":{"start":{"line":1,"column":1},"end":{"line":1,"column":1}},"html":"<span class=\"katex\"><span class=\"katex-mathml\"><math xmlns=\"http://www.w3.org/1998/Math/MathML\"><semantics><mrow><mi mathvariant=\"normal\">∀</mi><mi>B</mi><mo separator=\"true\">,</mo><mi>C</mi><mo>∈</mo><mi>X</mi><mspace width=\"1em\"/><mi>B</mi><mo>→</mo><mi>C</mi><mo>=</mo><mo>+</mo></mrow><annotation encoding=\"application/x-tex\">\\forall B, C \\in X \\quad B \\rightarrow C = +</annotation></semantics></math></span><span class=\"katex-html\" aria-hidden=\"true\"><span class=\"base\"><span class=\"strut\" style=\"height:0.8889em;vertical-align:-0.1944em;\"></span><span class=\"mord\">∀</span><span class=\"mord mathnormal\" style=\"margin-right:0.05017em;\">B</span><span class=\"mpunct\">,</span><span class=\"mspace\" style=\"margin-right:0.1667em;\"></span><span class=\"mord mathnormal\" style=\"margin-right:0.07153em;\">C</span><span class=\"mspace\" style=\"margin-right:0.2778em;\"></span><span class=\"mrel\">∈</span><span class=\"mspace\" style=\"margin-right:0.2778em;\"></span></span><span class=\"base\"><span class=\"strut\" style=\"height:0.6833em;\"></span><span class=\"mord mathnormal\" style=\"margin-right:0.07847em;\">X</span><span class=\"mspace\" style=\"margin-right:1em;\"></span><span class=\"mord mathnormal\" style=\"margin-right:0.05017em;\">B</span><span class=\"mspace\" style=\"margin-right:0.2778em;\"></span><span class=\"mrel\">→</span><span class=\"mspace\" style=\"margin-right:0.2778em;\"></span></span><span class=\"base\"><span class=\"strut\" style=\"height:0.6833em;\"></span><span class=\"mord mathnormal\" style=\"margin-right:0.07153em;\">C</span><span class=\"mspace\" style=\"margin-right:0.2778em;\"></span><span class=\"mrel\">=</span><span class=\"mspace\" style=\"margin-right:0.2778em;\"></span></span><span class=\"base\"><span class=\"strut\" style=\"height:0.6667em;vertical-align:-0.0833em;\"></span><span class=\"mord\">+</span></span></span></span>","key":"BpJW3XZNr4"}],"identifier":"condition-1-forall-b-c-in-x-quad-b-rightarrow-c","label":"Condition 1: \\forall B, C \\in X \\quad B \\rightarrow C = +","html_id":"condition-1-forall-b-c-in-x-quad-b-rightarrow-c","implicit":true,"key":"c4J5Irz5Tr"},{"type":"list","ordered":false,"spread":false,"position":{"start":{"line":3,"column":1},"end":{"line":7,"column":1}},"children":[{"type":"listItem","spread":true,"position":{"start":{"line":3,"column":1},"end":{"line":3,"column":1}},"children":[{"type":"text","value":"Let ","position":{"start":{"line":3,"column":1},"end":{"line":3,"column":1}},"key":"FlTyLF1LtT"},{"type":"inlineMath","value":"B, C \\in X","position":{"start":{"line":3,"column":1},"end":{"line":3,"column":1}},"html":"<span class=\"katex\"><span class=\"katex-mathml\"><math xmlns=\"http://www.w3.org/1998/Math/MathML\"><semantics><mrow><mi>B</mi><mo separator=\"true\">,</mo><mi>C</mi><mo>∈</mo><mi>X</mi></mrow><annotation encoding=\"application/x-tex\">B, C \\in X</annotation></semantics></math></span><span class=\"katex-html\" aria-hidden=\"true\"><span class=\"base\"><span class=\"strut\" style=\"height:0.8778em;vertical-align:-0.1944em;\"></span><span class=\"mord mathnormal\" style=\"margin-right:0.05017em;\">B</span><span class=\"mpunct\">,</span><span class=\"mspace\" style=\"margin-right:0.1667em;\"></span><span class=\"mord mathnormal\" style=\"margin-right:0.07153em;\">C</span><span class=\"mspace\" style=\"margin-right:0.2778em;\"></span><span class=\"mrel\">∈</span><span class=\"mspace\" style=\"margin-right:0.2778em;\"></span></span><span class=\"base\"><span class=\"strut\" style=\"height:0.6833em;\"></span><span class=\"mord mathnormal\" style=\"margin-right:0.07847em;\">X</span></span></span></span>","key":"XOJWAermsL"}],"key":"EjZiCN4SL0"},{"type":"listItem","spread":true,"position":{"start":{"line":4,"column":1},"end":{"line":4,"column":1}},"children":[{"type":"text","value":"We know ","position":{"start":{"line":4,"column":1},"end":{"line":4,"column":1}},"key":"ZzEy0orSCC"},{"type":"inlineMath","value":"A \\rightarrow B = +","position":{"start":{"line":4,"column":1},"end":{"line":4,"column":1}},"html":"<span class=\"katex\"><span class=\"katex-mathml\"><math xmlns=\"http://www.w3.org/1998/Math/MathML\"><semantics><mrow><mi>A</mi><mo>→</mo><mi>B</mi><mo>=</mo><mo>+</mo></mrow><annotation encoding=\"application/x-tex\">A \\rightarrow B = +</annotation></semantics></math></span><span class=\"katex-html\" aria-hidden=\"true\"><span class=\"base\"><span class=\"strut\" style=\"height:0.6833em;\"></span><span class=\"mord mathnormal\">A</span><span class=\"mspace\" style=\"margin-right:0.2778em;\"></span><span class=\"mrel\">→</span><span class=\"mspace\" style=\"margin-right:0.2778em;\"></span></span><span class=\"base\"><span class=\"strut\" style=\"height:0.6833em;\"></span><span class=\"mord mathnormal\" style=\"margin-right:0.05017em;\">B</span><span class=\"mspace\" style=\"margin-right:0.2778em;\"></span><span class=\"mrel\">=</span><span class=\"mspace\" style=\"margin-right:0.2778em;\"></span></span><span class=\"base\"><span class=\"strut\" style=\"height:0.6667em;vertical-align:-0.0833em;\"></span><span class=\"mord\">+</span></span></span></span>","key":"z0UFzyXwrd"},{"type":"text","value":" and ","position":{"start":{"line":4,"column":1},"end":{"line":4,"column":1}},"key":"lkH5PbRgOR"},{"type":"inlineMath","value":"A \\rightarrow C = +","position":{"start":{"line":4,"column":1},"end":{"line":4,"column":1}},"html":"<span class=\"katex\"><span class=\"katex-mathml\"><math xmlns=\"http://www.w3.org/1998/Math/MathML\"><semantics><mrow><mi>A</mi><mo>→</mo><mi>C</mi><mo>=</mo><mo>+</mo></mrow><annotation encoding=\"application/x-tex\">A \\rightarrow C = +</annotation></semantics></math></span><span class=\"katex-html\" aria-hidden=\"true\"><span class=\"base\"><span class=\"strut\" style=\"height:0.6833em;\"></span><span class=\"mord mathnormal\">A</span><span class=\"mspace\" style=\"margin-right:0.2778em;\"></span><span class=\"mrel\">→</span><span class=\"mspace\" style=\"margin-right:0.2778em;\"></span></span><span class=\"base\"><span class=\"strut\" style=\"height:0.6833em;\"></span><span class=\"mord mathnormal\" style=\"margin-right:0.07153em;\">C</span><span class=\"mspace\" style=\"margin-right:0.2778em;\"></span><span class=\"mrel\">=</span><span class=\"mspace\" style=\"margin-right:0.2778em;\"></span></span><span class=\"base\"><span class=\"strut\" style=\"height:0.6667em;vertical-align:-0.0833em;\"></span><span class=\"mord\">+</span></span></span></span>","key":"rwWJw6YzpF"}],"key":"u3lg8qdvBa"},{"type":"listItem","spread":true,"position":{"start":{"line":5,"column":1},"end":{"line":5,"column":1}},"children":[{"type":"text","value":"Because graph is balanced, this triangle must have 1 or 3 +","position":{"start":{"line":5,"column":1},"end":{"line":5,"column":1}},"key":"r1157d8nO4"}],"key":"PGqUw82eS3"},{"type":"listItem","spread":true,"position":{"start":{"line":6,"column":1},"end":{"line":6,"column":1}},"children":[{"type":"text","value":"There are already 2, so it must be that ","position":{"start":{"line":6,"column":1},"end":{"line":6,"column":1}},"key":"niJmvefZ6c"},{"type":"inlineMath","value":"B \\rightarrow C = +","position":{"start":{"line":6,"column":1},"end":{"line":6,"column":1}},"html":"<span class=\"katex\"><span class=\"katex-mathml\"><math xmlns=\"http://www.w3.org/1998/Math/MathML\"><semantics><mrow><mi>B</mi><mo>→</mo><mi>C</mi><mo>=</mo><mo>+</mo></mrow><annotation encoding=\"application/x-tex\">B \\rightarrow C = +</annotation></semantics></math></span><span class=\"katex-html\" aria-hidden=\"true\"><span class=\"base\"><span class=\"strut\" style=\"height:0.6833em;\"></span><span class=\"mord mathnormal\" style=\"margin-right:0.05017em;\">B</span><span class=\"mspace\" style=\"margin-right:0.2778em;\"></span><span class=\"mrel\">→</span><span class=\"mspace\" style=\"margin-right:0.2778em;\"></span></span><span class=\"base\"><span class=\"strut\" style=\"height:0.6833em;\"></span><span class=\"mord mathnormal\" style=\"margin-right:0.07153em;\">C</span><span class=\"mspace\" style=\"margin-right:0.2778em;\"></span><span class=\"mrel\">=</span><span class=\"mspace\" style=\"margin-right:0.2778em;\"></span></span><span class=\"base\"><span class=\"strut\" style=\"height:0.6667em;vertical-align:-0.0833em;\"></span><span class=\"mord\">+</span></span></span></span>","key":"ZJVoFTn146"}],"key":"eNrQPSUEB4"},{"type":"listItem","spread":true,"position":{"start":{"line":7,"column":1},"end":{"line":7,"column":1}},"children":[{"type":"text","value":"B, C were arbitrary, so this part is proven","position":{"start":{"line":7,"column":1},"end":{"line":7,"column":1}},"key":"TUUkdVO4dr"}],"key":"yvHdCIhIPb"}],"key":"U8zGQBOI1y"}],"visibility":"show","key":"QY6oh1ak3O"},{"type":"block","kind":"notebook-content","data":{"slideshow":{"slide_type":"fragment"},"tags":[]},"children":[{"type":"heading","depth":4,"position":{"start":{"line":1,"column":1},"end":{"line":1,"column":1}},"children":[{"type":"text","value":"Condition 2: ","position":{"start":{"line":1,"column":1},"end":{"line":1,"column":1}},"key":"BTsB5EQor5"},{"type":"inlineMath","value":"\\forall D, E \\in Y \\quad D \\rightarrow E = +","position":{"start":{"line":1,"column":1},"end":{"line":1,"column":1}},"html":"<span class=\"katex\"><span class=\"katex-mathml\"><math xmlns=\"http://www.w3.org/1998/Math/MathML\"><semantics><mrow><mi mathvariant=\"normal\">∀</mi><mi>D</mi><mo separator=\"true\">,</mo><mi>E</mi><mo>∈</mo><mi>Y</mi><mspace width=\"1em\"/><mi>D</mi><mo>→</mo><mi>E</mi><mo>=</mo><mo>+</mo></mrow><annotation encoding=\"application/x-tex\">\\forall D, E \\in Y \\quad D \\rightarrow E = +</annotation></semantics></math></span><span class=\"katex-html\" aria-hidden=\"true\"><span class=\"base\"><span class=\"strut\" style=\"height:0.8889em;vertical-align:-0.1944em;\"></span><span class=\"mord\">∀</span><span class=\"mord mathnormal\" style=\"margin-right:0.02778em;\">D</span><span class=\"mpunct\">,</span><span class=\"mspace\" style=\"margin-right:0.1667em;\"></span><span class=\"mord mathnormal\" style=\"margin-right:0.05764em;\">E</span><span class=\"mspace\" style=\"margin-right:0.2778em;\"></span><span class=\"mrel\">∈</span><span class=\"mspace\" style=\"margin-right:0.2778em;\"></span></span><span class=\"base\"><span class=\"strut\" style=\"height:0.6833em;\"></span><span class=\"mord mathnormal\" style=\"margin-right:0.22222em;\">Y</span><span class=\"mspace\" style=\"margin-right:1em;\"></span><span class=\"mord mathnormal\" style=\"margin-right:0.02778em;\">D</span><span class=\"mspace\" style=\"margin-right:0.2778em;\"></span><span class=\"mrel\">→</span><span class=\"mspace\" style=\"margin-right:0.2778em;\"></span></span><span class=\"base\"><span class=\"strut\" style=\"height:0.6833em;\"></span><span class=\"mord mathnormal\" style=\"margin-right:0.05764em;\">E</span><span class=\"mspace\" style=\"margin-right:0.2778em;\"></span><span class=\"mrel\">=</span><span class=\"mspace\" style=\"margin-right:0.2778em;\"></span></span><span class=\"base\"><span class=\"strut\" style=\"height:0.6667em;vertical-align:-0.0833em;\"></span><span class=\"mord\">+</span></span></span></span>","key":"iRVyFvByBD"}],"identifier":"condition-2-forall-d-e-in-y-quad-d-rightarrow-e","label":"Condition 2: \\forall D, E \\in Y \\quad D \\rightarrow E = +","html_id":"condition-2-forall-d-e-in-y-quad-d-rightarrow-e","implicit":true,"key":"SekQMdQHBn"},{"type":"list","ordered":false,"spread":false,"position":{"start":{"line":3,"column":1},"end":{"line":7,"column":1}},"children":[{"type":"listItem","spread":true,"position":{"start":{"line":3,"column":1},"end":{"line":3,"column":1}},"children":[{"type":"text","value":"Let ","position":{"start":{"line":3,"column":1},"end":{"line":3,"column":1}},"key":"pPkDqLx2rc"},{"type":"inlineMath","value":"D, E \\in Y","position":{"start":{"line":3,"column":1},"end":{"line":3,"column":1}},"html":"<span class=\"katex\"><span class=\"katex-mathml\"><math xmlns=\"http://www.w3.org/1998/Math/MathML\"><semantics><mrow><mi>D</mi><mo separator=\"true\">,</mo><mi>E</mi><mo>∈</mo><mi>Y</mi></mrow><annotation encoding=\"application/x-tex\">D, E \\in Y</annotation></semantics></math></span><span class=\"katex-html\" aria-hidden=\"true\"><span class=\"base\"><span class=\"strut\" style=\"height:0.8778em;vertical-align:-0.1944em;\"></span><span class=\"mord mathnormal\" style=\"margin-right:0.02778em;\">D</span><span class=\"mpunct\">,</span><span class=\"mspace\" style=\"margin-right:0.1667em;\"></span><span class=\"mord mathnormal\" style=\"margin-right:0.05764em;\">E</span><span class=\"mspace\" style=\"margin-right:0.2778em;\"></span><span class=\"mrel\">∈</span><span class=\"mspace\" style=\"margin-right:0.2778em;\"></span></span><span class=\"base\"><span class=\"strut\" style=\"height:0.6833em;\"></span><span class=\"mord mathnormal\" style=\"margin-right:0.22222em;\">Y</span></span></span></span>","key":"pY6caDakB8"}],"key":"fuURJ0Cm7c"},{"type":"listItem","spread":true,"position":{"start":{"line":4,"column":1},"end":{"line":4,"column":1}},"children":[{"type":"text","value":"We know ","position":{"start":{"line":4,"column":1},"end":{"line":4,"column":1}},"key":"L8MAP6WBcS"},{"type":"inlineMath","value":"A \\rightarrow D = -","position":{"start":{"line":4,"column":1},"end":{"line":4,"column":1}},"html":"<span class=\"katex\"><span class=\"katex-mathml\"><math xmlns=\"http://www.w3.org/1998/Math/MathML\"><semantics><mrow><mi>A</mi><mo>→</mo><mi>D</mi><mo>=</mo><mo>−</mo></mrow><annotation encoding=\"application/x-tex\">A \\rightarrow D = -</annotation></semantics></math></span><span class=\"katex-html\" aria-hidden=\"true\"><span class=\"base\"><span class=\"strut\" style=\"height:0.6833em;\"></span><span class=\"mord mathnormal\">A</span><span class=\"mspace\" style=\"margin-right:0.2778em;\"></span><span class=\"mrel\">→</span><span class=\"mspace\" style=\"margin-right:0.2778em;\"></span></span><span class=\"base\"><span class=\"strut\" style=\"height:0.6833em;\"></span><span class=\"mord mathnormal\" style=\"margin-right:0.02778em;\">D</span><span class=\"mspace\" style=\"margin-right:0.2778em;\"></span><span class=\"mrel\">=</span><span class=\"mspace\" style=\"margin-right:0.2778em;\"></span></span><span class=\"base\"><span class=\"strut\" style=\"height:0.6667em;vertical-align:-0.0833em;\"></span><span class=\"mord\">−</span></span></span></span>","key":"Nr8dACikNb"},{"type":"text","value":" and ","position":{"start":{"line":4,"column":1},"end":{"line":4,"column":1}},"key":"qoxwkjjOfB"},{"type":"inlineMath","value":"A \\rightarrow E = -","position":{"start":{"line":4,"column":1},"end":{"line":4,"column":1}},"html":"<span class=\"katex\"><span class=\"katex-mathml\"><math xmlns=\"http://www.w3.org/1998/Math/MathML\"><semantics><mrow><mi>A</mi><mo>→</mo><mi>E</mi><mo>=</mo><mo>−</mo></mrow><annotation encoding=\"application/x-tex\">A \\rightarrow E = -</annotation></semantics></math></span><span class=\"katex-html\" aria-hidden=\"true\"><span class=\"base\"><span class=\"strut\" style=\"height:0.6833em;\"></span><span class=\"mord mathnormal\">A</span><span class=\"mspace\" style=\"margin-right:0.2778em;\"></span><span class=\"mrel\">→</span><span class=\"mspace\" style=\"margin-right:0.2778em;\"></span></span><span class=\"base\"><span class=\"strut\" style=\"height:0.6833em;\"></span><span class=\"mord mathnormal\" style=\"margin-right:0.05764em;\">E</span><span class=\"mspace\" style=\"margin-right:0.2778em;\"></span><span class=\"mrel\">=</span><span class=\"mspace\" style=\"margin-right:0.2778em;\"></span></span><span class=\"base\"><span class=\"strut\" style=\"height:0.6667em;vertical-align:-0.0833em;\"></span><span class=\"mord\">−</span></span></span></span>","key":"Pider05cSd"}],"key":"FQpl3Oc3BZ"},{"type":"listItem","spread":true,"position":{"start":{"line":5,"column":1},"end":{"line":5,"column":1}},"children":[{"type":"text","value":"Because graph is balanced, this triangle must have 1 or 3 +","position":{"start":{"line":5,"column":1},"end":{"line":5,"column":1}},"key":"iFthr9U200"}],"key":"k92sJp2lGR"},{"type":"listItem","spread":true,"position":{"start":{"line":6,"column":1},"end":{"line":6,"column":1}},"children":[{"type":"text","value":"There no + and only one option left, so it must be that ","position":{"start":{"line":6,"column":1},"end":{"line":6,"column":1}},"key":"IZXCz4itJL"},{"type":"inlineMath","value":"D \\rightarrow E = +","position":{"start":{"line":6,"column":1},"end":{"line":6,"column":1}},"html":"<span class=\"katex\"><span class=\"katex-mathml\"><math xmlns=\"http://www.w3.org/1998/Math/MathML\"><semantics><mrow><mi>D</mi><mo>→</mo><mi>E</mi><mo>=</mo><mo>+</mo></mrow><annotation encoding=\"application/x-tex\">D \\rightarrow E = +</annotation></semantics></math></span><span class=\"katex-html\" aria-hidden=\"true\"><span class=\"base\"><span class=\"strut\" style=\"height:0.6833em;\"></span><span class=\"mord mathnormal\" style=\"margin-right:0.02778em;\">D</span><span class=\"mspace\" style=\"margin-right:0.2778em;\"></span><span class=\"mrel\">→</span><span class=\"mspace\" style=\"margin-right:0.2778em;\"></span></span><span class=\"base\"><span class=\"strut\" style=\"height:0.6833em;\"></span><span class=\"mord mathnormal\" style=\"margin-right:0.05764em;\">E</span><span class=\"mspace\" style=\"margin-right:0.2778em;\"></span><span class=\"mrel\">=</span><span class=\"mspace\" style=\"margin-right:0.2778em;\"></span></span><span class=\"base\"><span class=\"strut\" style=\"height:0.6667em;vertical-align:-0.0833em;\"></span><span class=\"mord\">+</span></span></span></span>","key":"mcoFUZGEgq"}],"key":"J8AuIVvq3F"},{"type":"listItem","spread":true,"position":{"start":{"line":7,"column":1},"end":{"line":7,"column":1}},"children":[{"type":"text","value":"D, E were arbitrary, so this part is proven","position":{"start":{"line":7,"column":1},"end":{"line":7,"column":1}},"key":"z1AcUGMbg1"}],"key":"iStFSB4Sl3"}],"key":"yGZjiJyC4J"}],"visibility":"show","key":"SvvRPoMnLc"},{"type":"block","kind":"notebook-content","data":{"slideshow":{"slide_type":"fragment"},"tags":[]},"children":[{"type":"heading","depth":4,"position":{"start":{"line":1,"column":1},"end":{"line":1,"column":1}},"children":[{"type":"text","value":"Condition 3: ","position":{"start":{"line":1,"column":1},"end":{"line":1,"column":1}},"key":"PYss7w2Or3"},{"type":"inlineMath","value":"\\forall B \\in X","position":{"start":{"line":1,"column":1},"end":{"line":1,"column":1}},"html":"<span class=\"katex\"><span class=\"katex-mathml\"><math xmlns=\"http://www.w3.org/1998/Math/MathML\"><semantics><mrow><mi mathvariant=\"normal\">∀</mi><mi>B</mi><mo>∈</mo><mi>X</mi></mrow><annotation encoding=\"application/x-tex\">\\forall B \\in X</annotation></semantics></math></span><span class=\"katex-html\" aria-hidden=\"true\"><span class=\"base\"><span class=\"strut\" style=\"height:0.7335em;vertical-align:-0.0391em;\"></span><span class=\"mord\">∀</span><span class=\"mord mathnormal\" style=\"margin-right:0.05017em;\">B</span><span class=\"mspace\" style=\"margin-right:0.2778em;\"></span><span class=\"mrel\">∈</span><span class=\"mspace\" style=\"margin-right:0.2778em;\"></span></span><span class=\"base\"><span class=\"strut\" style=\"height:0.6833em;\"></span><span class=\"mord mathnormal\" style=\"margin-right:0.07847em;\">X</span></span></span></span>","key":"cGlfZKNBT7"},{"type":"text","value":" and ","position":{"start":{"line":1,"column":1},"end":{"line":1,"column":1}},"key":"DXBnxDC33T"},{"type":"inlineMath","value":"E \\in Y \\quad B \\rightarrow E = -","position":{"start":{"line":1,"column":1},"end":{"line":1,"column":1}},"html":"<span class=\"katex\"><span class=\"katex-mathml\"><math xmlns=\"http://www.w3.org/1998/Math/MathML\"><semantics><mrow><mi>E</mi><mo>∈</mo><mi>Y</mi><mspace width=\"1em\"/><mi>B</mi><mo>→</mo><mi>E</mi><mo>=</mo><mo>−</mo></mrow><annotation encoding=\"application/x-tex\">E \\in Y \\quad B \\rightarrow E = -</annotation></semantics></math></span><span class=\"katex-html\" aria-hidden=\"true\"><span class=\"base\"><span class=\"strut\" style=\"height:0.7224em;vertical-align:-0.0391em;\"></span><span class=\"mord mathnormal\" style=\"margin-right:0.05764em;\">E</span><span class=\"mspace\" style=\"margin-right:0.2778em;\"></span><span class=\"mrel\">∈</span><span class=\"mspace\" style=\"margin-right:0.2778em;\"></span></span><span class=\"base\"><span class=\"strut\" style=\"height:0.6833em;\"></span><span class=\"mord mathnormal\" style=\"margin-right:0.22222em;\">Y</span><span class=\"mspace\" style=\"margin-right:1em;\"></span><span class=\"mord mathnormal\" style=\"margin-right:0.05017em;\">B</span><span class=\"mspace\" style=\"margin-right:0.2778em;\"></span><span class=\"mrel\">→</span><span class=\"mspace\" style=\"margin-right:0.2778em;\"></span></span><span class=\"base\"><span class=\"strut\" style=\"height:0.6833em;\"></span><span class=\"mord mathnormal\" style=\"margin-right:0.05764em;\">E</span><span class=\"mspace\" style=\"margin-right:0.2778em;\"></span><span class=\"mrel\">=</span><span class=\"mspace\" style=\"margin-right:0.2778em;\"></span></span><span class=\"base\"><span class=\"strut\" style=\"height:0.6667em;vertical-align:-0.0833em;\"></span><span class=\"mord\">−</span></span></span></span>","key":"aFVaYUnJKv"}],"identifier":"condition-3-forall-b-in-x-and-e-in-y-quad-b-rightarrow-e","label":"Condition 3: \\forall B \\in X and E \\in Y \\quad B \\rightarrow E = -","html_id":"condition-3-forall-b-in-x-and-e-in-y-quad-b-rightarrow-e","implicit":true,"key":"XUU6fiTAEu"},{"type":"list","ordered":false,"spread":false,"position":{"start":{"line":3,"column":1},"end":{"line":7,"column":1}},"children":[{"type":"listItem","spread":true,"position":{"start":{"line":3,"column":1},"end":{"line":3,"column":1}},"children":[{"type":"text","value":"Let ","position":{"start":{"line":3,"column":1},"end":{"line":3,"column":1}},"key":"rVeEysK6II"},{"type":"inlineMath","value":"B \\in X","position":{"start":{"line":3,"column":1},"end":{"line":3,"column":1}},"html":"<span class=\"katex\"><span class=\"katex-mathml\"><math xmlns=\"http://www.w3.org/1998/Math/MathML\"><semantics><mrow><mi>B</mi><mo>∈</mo><mi>X</mi></mrow><annotation encoding=\"application/x-tex\">B \\in X</annotation></semantics></math></span><span class=\"katex-html\" aria-hidden=\"true\"><span class=\"base\"><span class=\"strut\" style=\"height:0.7224em;vertical-align:-0.0391em;\"></span><span class=\"mord mathnormal\" style=\"margin-right:0.05017em;\">B</span><span class=\"mspace\" style=\"margin-right:0.2778em;\"></span><span class=\"mrel\">∈</span><span class=\"mspace\" style=\"margin-right:0.2778em;\"></span></span><span class=\"base\"><span class=\"strut\" style=\"height:0.6833em;\"></span><span class=\"mord mathnormal\" style=\"margin-right:0.07847em;\">X</span></span></span></span>","key":"qxQjQ2kWc6"},{"type":"text","value":" and ","position":{"start":{"line":3,"column":1},"end":{"line":3,"column":1}},"key":"WOlKafmVJR"},{"type":"inlineMath","value":"D \\in Y","position":{"start":{"line":3,"column":1},"end":{"line":3,"column":1}},"html":"<span class=\"katex\"><span class=\"katex-mathml\"><math xmlns=\"http://www.w3.org/1998/Math/MathML\"><semantics><mrow><mi>D</mi><mo>∈</mo><mi>Y</mi></mrow><annotation encoding=\"application/x-tex\">D \\in Y</annotation></semantics></math></span><span class=\"katex-html\" aria-hidden=\"true\"><span class=\"base\"><span class=\"strut\" style=\"height:0.7224em;vertical-align:-0.0391em;\"></span><span class=\"mord mathnormal\" style=\"margin-right:0.02778em;\">D</span><span class=\"mspace\" style=\"margin-right:0.2778em;\"></span><span class=\"mrel\">∈</span><span class=\"mspace\" style=\"margin-right:0.2778em;\"></span></span><span class=\"base\"><span class=\"strut\" style=\"height:0.6833em;\"></span><span class=\"mord mathnormal\" style=\"margin-right:0.22222em;\">Y</span></span></span></span>","key":"fnw9VDKVou"}],"key":"qu5OYLwhJm"},{"type":"listItem","spread":true,"position":{"start":{"line":4,"column":1},"end":{"line":4,"column":1}},"children":[{"type":"text","value":"We know ","position":{"start":{"line":4,"column":1},"end":{"line":4,"column":1}},"key":"gkRh2fJdSQ"},{"type":"inlineMath","value":"A \\rightarrow D = -","position":{"start":{"line":4,"column":1},"end":{"line":4,"column":1}},"html":"<span class=\"katex\"><span class=\"katex-mathml\"><math xmlns=\"http://www.w3.org/1998/Math/MathML\"><semantics><mrow><mi>A</mi><mo>→</mo><mi>D</mi><mo>=</mo><mo>−</mo></mrow><annotation encoding=\"application/x-tex\">A \\rightarrow D = -</annotation></semantics></math></span><span class=\"katex-html\" aria-hidden=\"true\"><span class=\"base\"><span class=\"strut\" style=\"height:0.6833em;\"></span><span class=\"mord mathnormal\">A</span><span class=\"mspace\" style=\"margin-right:0.2778em;\"></span><span class=\"mrel\">→</span><span class=\"mspace\" style=\"margin-right:0.2778em;\"></span></span><span class=\"base\"><span class=\"strut\" style=\"height:0.6833em;\"></span><span class=\"mord mathnormal\" style=\"margin-right:0.02778em;\">D</span><span class=\"mspace\" style=\"margin-right:0.2778em;\"></span><span class=\"mrel\">=</span><span class=\"mspace\" style=\"margin-right:0.2778em;\"></span></span><span class=\"base\"><span class=\"strut\" style=\"height:0.6667em;vertical-align:-0.0833em;\"></span><span class=\"mord\">−</span></span></span></span>","key":"Yskuw1ghxq"},{"type":"text","value":" and ","position":{"start":{"line":4,"column":1},"end":{"line":4,"column":1}},"key":"YL8P4oz5oy"},{"type":"inlineMath","value":"A \\rightarrow B = +","position":{"start":{"line":4,"column":1},"end":{"line":4,"column":1}},"html":"<span class=\"katex\"><span class=\"katex-mathml\"><math xmlns=\"http://www.w3.org/1998/Math/MathML\"><semantics><mrow><mi>A</mi><mo>→</mo><mi>B</mi><mo>=</mo><mo>+</mo></mrow><annotation encoding=\"application/x-tex\">A \\rightarrow B = +</annotation></semantics></math></span><span class=\"katex-html\" aria-hidden=\"true\"><span class=\"base\"><span class=\"strut\" style=\"height:0.6833em;\"></span><span class=\"mord mathnormal\">A</span><span class=\"mspace\" style=\"margin-right:0.2778em;\"></span><span class=\"mrel\">→</span><span class=\"mspace\" style=\"margin-right:0.2778em;\"></span></span><span class=\"base\"><span class=\"strut\" style=\"height:0.6833em;\"></span><span class=\"mord mathnormal\" style=\"margin-right:0.05017em;\">B</span><span class=\"mspace\" style=\"margin-right:0.2778em;\"></span><span class=\"mrel\">=</span><span class=\"mspace\" style=\"margin-right:0.2778em;\"></span></span><span class=\"base\"><span class=\"strut\" style=\"height:0.6667em;vertical-align:-0.0833em;\"></span><span class=\"mord\">+</span></span></span></span>","key":"XGLATKwszm"}],"key":"IvoLfBkI2S"},{"type":"listItem","spread":true,"position":{"start":{"line":5,"column":1},"end":{"line":5,"column":1}},"children":[{"type":"text","value":"Because graph is balanced, this triangle must have 1 or 3 +","position":{"start":{"line":5,"column":1},"end":{"line":5,"column":1}},"key":"y544zJ8ot2"}],"key":"b6W7JKEUKB"},{"type":"listItem","spread":true,"position":{"start":{"line":6,"column":1},"end":{"line":6,"column":1}},"children":[{"type":"text","value":"There is one + (","position":{"start":{"line":6,"column":1},"end":{"line":6,"column":1}},"key":"Xmvd4V5UdJ"},{"type":"inlineMath","value":"A \\rightarrow B","position":{"start":{"line":6,"column":1},"end":{"line":6,"column":1}},"html":"<span class=\"katex\"><span class=\"katex-mathml\"><math xmlns=\"http://www.w3.org/1998/Math/MathML\"><semantics><mrow><mi>A</mi><mo>→</mo><mi>B</mi></mrow><annotation encoding=\"application/x-tex\">A \\rightarrow B</annotation></semantics></math></span><span class=\"katex-html\" aria-hidden=\"true\"><span class=\"base\"><span class=\"strut\" style=\"height:0.6833em;\"></span><span class=\"mord mathnormal\">A</span><span class=\"mspace\" style=\"margin-right:0.2778em;\"></span><span class=\"mrel\">→</span><span class=\"mspace\" style=\"margin-right:0.2778em;\"></span></span><span class=\"base\"><span class=\"strut\" style=\"height:0.6833em;\"></span><span class=\"mord mathnormal\" style=\"margin-right:0.05017em;\">B</span></span></span></span>","key":"wsJPUtFE8f"},{"type":"text","value":") and only one option left, so it must be that ","position":{"start":{"line":6,"column":1},"end":{"line":6,"column":1}},"key":"Hkm5NOEQh9"},{"type":"inlineMath","value":"B \\rightarrow D = -","position":{"start":{"line":6,"column":1},"end":{"line":6,"column":1}},"html":"<span class=\"katex\"><span class=\"katex-mathml\"><math xmlns=\"http://www.w3.org/1998/Math/MathML\"><semantics><mrow><mi>B</mi><mo>→</mo><mi>D</mi><mo>=</mo><mo>−</mo></mrow><annotation encoding=\"application/x-tex\">B \\rightarrow D = -</annotation></semantics></math></span><span class=\"katex-html\" aria-hidden=\"true\"><span class=\"base\"><span class=\"strut\" style=\"height:0.6833em;\"></span><span class=\"mord mathnormal\" style=\"margin-right:0.05017em;\">B</span><span class=\"mspace\" style=\"margin-right:0.2778em;\"></span><span class=\"mrel\">→</span><span class=\"mspace\" style=\"margin-right:0.2778em;\"></span></span><span class=\"base\"><span class=\"strut\" style=\"height:0.6833em;\"></span><span class=\"mord mathnormal\" style=\"margin-right:0.02778em;\">D</span><span class=\"mspace\" style=\"margin-right:0.2778em;\"></span><span class=\"mrel\">=</span><span class=\"mspace\" style=\"margin-right:0.2778em;\"></span></span><span class=\"base\"><span class=\"strut\" style=\"height:0.6667em;vertical-align:-0.0833em;\"></span><span class=\"mord\">−</span></span></span></span>","key":"GpJ7TQREx3"}],"key":"ijDSdsl9Zy"},{"type":"listItem","spread":true,"position":{"start":{"line":7,"column":1},"end":{"line":7,"column":1}},"children":[{"type":"text","value":"B, D were arbitrary, so this part is proven","position":{"start":{"line":7,"column":1},"end":{"line":7,"column":1}},"key":"KUeH8d3tyn"}],"key":"Zn6ZAQ4KXi"}],"key":"ash2OGbhv1"}],"visibility":"show","key":"a7to37xNtc"},{"type":"block","kind":"notebook-content","data":{"slideshow":{"slide_type":"subslide"},"tags":[]},"children":[{"type":"heading","depth":3,"position":{"start":{"line":1,"column":1},"end":{"line":1,"column":1}},"children":[{"type":"text","value":"Summary","position":{"start":{"line":1,"column":1},"end":{"line":1,"column":1}},"key":"KmZyeRvmCi"}],"identifier":"summary","label":"Summary","html_id":"summary","implicit":true,"key":"nXfUaA5rsu"},{"type":"list","ordered":false,"spread":false,"position":{"start":{"line":3,"column":1},"end":{"line":4,"column":1}},"children":[{"type":"listItem","spread":true,"position":{"start":{"line":3,"column":1},"end":{"line":3,"column":1}},"children":[{"type":"text","value":"We’ve just proven that for any complete, balanced graph ","position":{"start":{"line":3,"column":1},"end":{"line":3,"column":1}},"key":"QJbyfiFudg"},{"type":"inlineMath","value":"G","position":{"start":{"line":3,"column":1},"end":{"line":3,"column":1}},"html":"<span class=\"katex\"><span class=\"katex-mathml\"><math xmlns=\"http://www.w3.org/1998/Math/MathML\"><semantics><mrow><mi>G</mi></mrow><annotation encoding=\"application/x-tex\">G</annotation></semantics></math></span><span class=\"katex-html\" aria-hidden=\"true\"><span class=\"base\"><span class=\"strut\" style=\"height:0.6833em;\"></span><span class=\"mord mathnormal\">G</span></span></span></span>","key":"UxwAT9nbbk"},{"type":"text","value":"; we can partition ","position":{"start":{"line":3,"column":1},"end":{"line":3,"column":1}},"key":"wxHooharfm"},{"type":"inlineMath","value":"G","position":{"start":{"line":3,"column":1},"end":{"line":3,"column":1}},"html":"<span class=\"katex\"><span class=\"katex-mathml\"><math xmlns=\"http://www.w3.org/1998/Math/MathML\"><semantics><mrow><mi>G</mi></mrow><annotation encoding=\"application/x-tex\">G</annotation></semantics></math></span><span class=\"katex-html\" aria-hidden=\"true\"><span class=\"base\"><span class=\"strut\" style=\"height:0.6833em;\"></span><span class=\"mord mathnormal\">G</span></span></span></span>","key":"uB0saGwpFx"},{"type":"text","value":" into sets ","position":{"start":{"line":3,"column":1},"end":{"line":3,"column":1}},"key":"yaC4sKbyOp"},{"type":"inlineMath","value":"X","position":{"start":{"line":3,"column":1},"end":{"line":3,"column":1}},"html":"<span class=\"katex\"><span class=\"katex-mathml\"><math xmlns=\"http://www.w3.org/1998/Math/MathML\"><semantics><mrow><mi>X</mi></mrow><annotation encoding=\"application/x-tex\">X</annotation></semantics></math></span><span class=\"katex-html\" aria-hidden=\"true\"><span class=\"base\"><span class=\"strut\" style=\"height:0.6833em;\"></span><span class=\"mord mathnormal\" style=\"margin-right:0.07847em;\">X</span></span></span></span>","key":"FghISDoHn8"},{"type":"text","value":" and ","position":{"start":{"line":3,"column":1},"end":{"line":3,"column":1}},"key":"jpR5Wc7OQQ"},{"type":"inlineMath","value":"Y","position":{"start":{"line":3,"column":1},"end":{"line":3,"column":1}},"html":"<span class=\"katex\"><span class=\"katex-mathml\"><math xmlns=\"http://www.w3.org/1998/Math/MathML\"><semantics><mrow><mi>Y</mi></mrow><annotation encoding=\"application/x-tex\">Y</annotation></semantics></math></span><span class=\"katex-html\" aria-hidden=\"true\"><span class=\"base\"><span class=\"strut\" style=\"height:0.6833em;\"></span><span class=\"mord mathnormal\" style=\"margin-right:0.22222em;\">Y</span></span></span></span>","key":"ACnEZhOMgu"},{"type":"text","value":" that satisfy the group structure of all friends or two groups of friends","position":{"start":{"line":3,"column":1},"end":{"line":3,"column":1}},"key":"ZKy9Sl6Y5p"}],"key":"sAIrlR2xbi"},{"type":"listItem","spread":true,"position":{"start":{"line":4,"column":1},"end":{"line":4,"column":1}},"children":[{"type":"text","value":"This has interesting implications for fields like social interactions, international relations, and online behavior","position":{"start":{"line":4,"column":1},"end":{"line":4,"column":1}},"key":"Kti5NFDRT9"}],"key":"DSfTmkxmi5"}],"key":"u1vLs121tu"}],"visibility":"show","key":"ZAmTbRKbvF"},{"type":"block","kind":"notebook-content","data":{"slideshow":{"slide_type":"slide"},"tags":[]},"children":[{"type":"heading","depth":2,"position":{"start":{"line":1,"column":1},"end":{"line":1,"column":1}},"children":[{"type":"text","value":"Application: International Relations","position":{"start":{"line":1,"column":1},"end":{"line":1,"column":1}},"key":"sdnaaNdfoV"}],"identifier":"application-international-relations","label":"Application: International Relations","html_id":"application-international-relations","implicit":true,"key":"RhcfTZRfxt"},{"type":"list","ordered":false,"spread":false,"position":{"start":{"line":3,"column":1},"end":{"line":3,"column":1}},"children":[{"type":"listItem","spread":true,"position":{"start":{"line":3,"column":1},"end":{"line":3,"column":1}},"children":[{"type":"text","value":"Consider the evolution of alliances in Europe between 1872 and 1907 as represented in the graphs below","position":{"start":{"line":3,"column":1},"end":{"line":3,"column":1}},"key":"dSml2MMXC5"}],"key":"KE6Fmd8FqQ"}],"key":"b9RBDRo5f3"}],"visibility":"show","key":"ejTEQza3f2"},{"type":"block","kind":"notebook-content","data":{"tags":[]},"children":[{"type":"image","url":"/build/d939c1c4aba39a33a2c920c2c07f11eb.png","alt":"https://compsosci-resources.s3.amazonaws.com/graph-theory-lectures/images/balance_international_relations.png","position":{"start":{"line":1,"column":1},"end":{"line":1,"column":1}},"key":"ALxirOGO7U","urlSource":"https://compsosci-resources.s3.amazonaws.com/graph-theory-lectures/images/balance_international_relations.png","urlOptimized":"/build/d939c1c4aba39a33a2c920c2c07f11eb.webp"}],"visibility":"show","key":"A1tWA9AYIc"}],"key":"UrSRuyMESh"},"references":{"cite":{"order":[],"data":{}}},"footer":{"navigation":{"prev":{"title":"Weighted Graphs","url":"/l04-02-weighted-graphs","group":"Graph Theory 2"},"next":{"title":"Production Networks","url":"/l05-01-production-networks","group":"Production Networks"}}},"domain":"http://localhost:3000"}